{
  "a_comp_cor_00": {
    "CumulativeVarianceExplained": 0.0532643294,
    "Mask": "combined",
    "Method": "aCompCor",
    "Retained": true,
    "SingularValue": 125.5085367108,
    "VarianceExplained": 0.0532643294
  },
  "a_comp_cor_01": {
    "CumulativeVarianceExplained": 0.0694602163,
    "Mask": "combined",
    "Method": "aCompCor",
    "Retained": true,
    "SingularValue": 69.2081757782,
    "VarianceExplained": 0.0161958869
  },
  "a_comp_cor_02": {
    "CumulativeVarianceExplained": 0.0833968179,
    "Mask": "combined",
    "Method": "aCompCor",
    "Retained": true,
    "SingularValue": 64.1997706302,
    "VarianceExplained": 0.0139366016
  },
  "a_comp_cor_03": {
    "CumulativeVarianceExplained": 0.095357241,
    "Mask": "combined",
    "Method": "aCompCor",
    "Retained": true,
    "SingularValue": 59.4741584691,
    "VarianceExplained": 0.0119604231
  },
  "a_comp_cor_04": {
    "CumulativeVarianceExplained": 0.106749533,
    "Mask": "combined",
    "Method": "aCompCor",
    "Retained": true,
    "SingularValue": 58.0444350432,
    "VarianceExplained": 0.011392292
  },
  "a_comp_cor_05": {
    "CumulativeVarianceExplained": 0.1167607196,
    "Mask": "combined",
    "Method": "aCompCor",
    "Retained": true,
    "SingularValue": 54.4123912275,
    "VarianceExplained": 0.0100111866
  },
  "a_comp_cor_06": {
    "CumulativeVarianceExplained": 0.1261021938,
    "Mask": "combined",
    "Method": "aCompCor",
    "Retained": true,
    "SingularValue": 52.5608939405,
    "VarianceExplained": 0.0093414742
  },
  "a_comp_cor_07": {
    "CumulativeVarianceExplained": 0.1344807994,
    "Mask": "combined",
    "Method": "aCompCor",
    "Retained": true,
    "SingularValue": 49.7783972268,
    "VarianceExplained": 0.0083786056
  },
  "a_comp_cor_08": {
    "CumulativeVarianceExplained": 0.1424936508,
    "Mask": "combined",
    "Method": "aCompCor",
    "Retained": true,
    "SingularValue": 48.6797766611,
    "VarianceExplained": 0.0080128513
  },
  "a_comp_cor_09": {
    "CumulativeVarianceExplained": 0.150173507,
    "Mask": "combined",
    "Method": "aCompCor",
    "Retained": true,
    "SingularValue": 47.6575355873,
    "VarianceExplained": 0.0076798563
  },
  "a_comp_cor_10": {
    "CumulativeVarianceExplained": 0.1578319137,
    "Mask": "combined",
    "Method": "aCompCor",
    "Retained": true,
    "SingularValue": 47.5909358873,
    "VarianceExplained": 0.0076584066
  },
  "a_comp_cor_11": {
    "CumulativeVarianceExplained": 0.1654327409,
    "Mask": "combined",
    "Method": "aCompCor",
    "Retained": true,
    "SingularValue": 47.4116931748,
    "VarianceExplained": 0.0076008272
  },
  "a_comp_cor_12": {
    "CumulativeVarianceExplained": 0.1728389651,
    "Mask": "combined",
    "Method": "aCompCor",
    "Retained": true,
    "SingularValue": 46.8008198405,
    "VarianceExplained": 0.0074062242
  },
  "a_comp_cor_13": {
    "CumulativeVarianceExplained": 0.1802195499,
    "Mask": "combined",
    "Method": "aCompCor",
    "Retained": true,
    "SingularValue": 46.7197403942,
    "VarianceExplained": 0.0073805848
  },
  "a_comp_cor_14": {
    "CumulativeVarianceExplained": 0.1874908073,
    "Mask": "combined",
    "Method": "aCompCor",
    "Retained": true,
    "SingularValue": 46.3724236856,
    "VarianceExplained": 0.0072712575
  },
  "a_comp_cor_15": {
    "CumulativeVarianceExplained": 0.1946622893,
    "Mask": "combined",
    "Method": "aCompCor",
    "Retained": true,
    "SingularValue": 46.0531657076,
    "VarianceExplained": 0.0071714819
  },
  "a_comp_cor_16": {
    "CumulativeVarianceExplained": 0.2017747854,
    "Mask": "combined",
    "Method": "aCompCor",
    "Retained": true,
    "SingularValue": 45.8633798959,
    "VarianceExplained": 0.0071124962
  },
  "a_comp_cor_17": {
    "CumulativeVarianceExplained": 0.2088730775,
    "Mask": "combined",
    "Method": "aCompCor",
    "Retained": true,
    "SingularValue": 45.8175610267,
    "VarianceExplained": 0.0070982921
  },
  "a_comp_cor_18": {
    "CumulativeVarianceExplained": 0.2158542937,
    "Mask": "combined",
    "Method": "aCompCor",
    "Retained": true,
    "SingularValue": 45.4381434672,
    "VarianceExplained": 0.0069812162
  },
  "a_comp_cor_19": {
    "CumulativeVarianceExplained": 0.2227800046,
    "Mask": "combined",
    "Method": "aCompCor",
    "Retained": true,
    "SingularValue": 45.2571510671,
    "VarianceExplained": 0.0069257108
  },
  "a_comp_cor_20": {
    "CumulativeVarianceExplained": 0.2296222871,
    "Mask": "combined",
    "Method": "aCompCor",
    "Retained": true,
    "SingularValue": 44.983737625,
    "VarianceExplained": 0.0068422826
  },
  "a_comp_cor_21": {
    "CumulativeVarianceExplained": 0.2364081787,
    "Mask": "combined",
    "Method": "aCompCor",
    "Retained": true,
    "SingularValue": 44.797986159,
    "VarianceExplained": 0.0067858915
  },
  "a_comp_cor_22": {
    "CumulativeVarianceExplained": 0.2431423611,
    "Mask": "combined",
    "Method": "aCompCor",
    "Retained": true,
    "SingularValue": 44.6269774029,
    "VarianceExplained": 0.0067341824
  },
  "a_comp_cor_23": {
    "CumulativeVarianceExplained": 0.2498203079,
    "Mask": "combined",
    "Method": "aCompCor",
    "Retained": true,
    "SingularValue": 44.4402517876,
    "VarianceExplained": 0.0066779468
  },
  "a_comp_cor_24": {
    "CumulativeVarianceExplained": 0.2564294085,
    "Mask": "combined",
    "Method": "aCompCor",
    "Retained": true,
    "SingularValue": 44.2105804082,
    "VarianceExplained": 0.0066091006
  },
  "a_comp_cor_25": {
    "CumulativeVarianceExplained": 0.2629344906,
    "Mask": "combined",
    "Method": "aCompCor",
    "Retained": true,
    "SingularValue": 43.8612924345,
    "VarianceExplained": 0.0065050821
  },
  "a_comp_cor_26": {
    "CumulativeVarianceExplained": 0.2693948589,
    "Mask": "combined",
    "Method": "aCompCor",
    "Retained": true,
    "SingularValue": 43.7102884492,
    "VarianceExplained": 0.0064603683
  },
  "a_comp_cor_27": {
    "CumulativeVarianceExplained": 0.2758339503,
    "Mask": "combined",
    "Method": "aCompCor",
    "Retained": true,
    "SingularValue": 43.6382502768,
    "VarianceExplained": 0.0064390914
  },
  "a_comp_cor_28": {
    "CumulativeVarianceExplained": 0.2821890282,
    "Mask": "combined",
    "Method": "aCompCor",
    "Retained": true,
    "SingularValue": 43.3526326237,
    "VarianceExplained": 0.006355078
  },
  "a_comp_cor_29": {
    "CumulativeVarianceExplained": 0.288523152,
    "Mask": "combined",
    "Method": "aCompCor",
    "Retained": true,
    "SingularValue": 43.2811015727,
    "VarianceExplained": 0.0063341237
  },
  "a_comp_cor_30": {
    "CumulativeVarianceExplained": 0.2948090697,
    "Mask": "combined",
    "Method": "aCompCor",
    "Retained": true,
    "SingularValue": 43.1160911019,
    "VarianceExplained": 0.0062859177
  },
  "a_comp_cor_31": {
    "CumulativeVarianceExplained": 0.3009871445,
    "Mask": "combined",
    "Method": "aCompCor",
    "Retained": true,
    "SingularValue": 42.7446351151,
    "VarianceExplained": 0.0061780748
  },
  "a_comp_cor_32": {
    "CumulativeVarianceExplained": 0.3071424594,
    "Mask": "combined",
    "Method": "aCompCor",
    "Retained": true,
    "SingularValue": 42.6658275159,
    "VarianceExplained": 0.0061553149
  },
  "a_comp_cor_33": {
    "CumulativeVarianceExplained": 0.3132521366,
    "Mask": "combined",
    "Method": "aCompCor",
    "Retained": true,
    "SingularValue": 42.5073632237,
    "VarianceExplained": 0.0061096772
  },
  "a_comp_cor_34": {
    "CumulativeVarianceExplained": 0.3193370892,
    "Mask": "combined",
    "Method": "aCompCor",
    "Retained": true,
    "SingularValue": 42.4212668227,
    "VarianceExplained": 0.0060849526
  },
  "a_comp_cor_35": {
    "CumulativeVarianceExplained": 0.3253151732,
    "Mask": "combined",
    "Method": "aCompCor",
    "Retained": true,
    "SingularValue": 42.0470994771,
    "VarianceExplained": 0.005978084
  },
  "a_comp_cor_36": {
    "CumulativeVarianceExplained": 0.3312320811,
    "Mask": "combined",
    "Method": "aCompCor",
    "Retained": true,
    "SingularValue": 41.8314038896,
    "VarianceExplained": 0.0059169079
  },
  "a_comp_cor_37": {
    "CumulativeVarianceExplained": 0.3370708946,
    "Mask": "combined",
    "Method": "aCompCor",
    "Retained": true,
    "SingularValue": 41.5544306015,
    "VarianceExplained": 0.0058388135
  },
  "a_comp_cor_38": {
    "CumulativeVarianceExplained": 0.3428914901,
    "Mask": "combined",
    "Method": "aCompCor",
    "Retained": true,
    "SingularValue": 41.489551909,
    "VarianceExplained": 0.0058205955
  },
  "a_comp_cor_39": {
    "CumulativeVarianceExplained": 0.3486815179,
    "Mask": "combined",
    "Method": "aCompCor",
    "Retained": true,
    "SingularValue": 41.3804642219,
    "VarianceExplained": 0.0057900278
  },
  "a_comp_cor_40": {
    "CumulativeVarianceExplained": 0.3544411442,
    "Mask": "combined",
    "Method": "aCompCor",
    "Retained": true,
    "SingularValue": 41.2716835001,
    "VarianceExplained": 0.0057596262
  },
  "a_comp_cor_41": {
    "CumulativeVarianceExplained": 0.3601627687,
    "Mask": "combined",
    "Method": "aCompCor",
    "Retained": true,
    "SingularValue": 41.1353039726,
    "VarianceExplained": 0.0057216245
  },
  "a_comp_cor_42": {
    "CumulativeVarianceExplained": 0.365830958,
    "Mask": "combined",
    "Method": "aCompCor",
    "Retained": true,
    "SingularValue": 40.942768636,
    "VarianceExplained": 0.0056681893
  },
  "a_comp_cor_43": {
    "CumulativeVarianceExplained": 0.3714917369,
    "Mask": "combined",
    "Method": "aCompCor",
    "Retained": true,
    "SingularValue": 40.9159963926,
    "VarianceExplained": 0.0056607789
  },
  "a_comp_cor_44": {
    "CumulativeVarianceExplained": 0.3771137245,
    "Mask": "combined",
    "Method": "aCompCor",
    "Retained": true,
    "SingularValue": 40.7755639739,
    "VarianceExplained": 0.0056219876
  },
  "a_comp_cor_45": {
    "CumulativeVarianceExplained": 0.3826639112,
    "Mask": "combined",
    "Method": "aCompCor",
    "Retained": true,
    "SingularValue": 40.5143457398,
    "VarianceExplained": 0.0055501867
  },
  "a_comp_cor_46": {
    "CumulativeVarianceExplained": 0.3881733116,
    "Mask": "combined",
    "Method": "aCompCor",
    "Retained": true,
    "SingularValue": 40.3652086837,
    "VarianceExplained": 0.0055094004
  },
  "a_comp_cor_47": {
    "CumulativeVarianceExplained": 0.3936340456,
    "Mask": "combined",
    "Method": "aCompCor",
    "Retained": true,
    "SingularValue": 40.18653349,
    "VarianceExplained": 0.005460734
  },
  "a_comp_cor_48": {
    "CumulativeVarianceExplained": 0.3990868579,
    "Mask": "combined",
    "Method": "aCompCor",
    "Retained": true,
    "SingularValue": 40.1573744519,
    "VarianceExplained": 0.0054528123
  },
  "a_comp_cor_49": {
    "CumulativeVarianceExplained": 0.4044995319,
    "Mask": "combined",
    "Method": "aCompCor",
    "Retained": true,
    "SingularValue": 40.0093012363,
    "VarianceExplained": 0.0054126739
  },
  "a_comp_cor_50": {
    "CumulativeVarianceExplained": 0.4098730024,
    "Mask": "combined",
    "Method": "aCompCor",
    "Retained": true,
    "SingularValue": 39.8641466439,
    "VarianceExplained": 0.0053734706
  },
  "a_comp_cor_51": {
    "CumulativeVarianceExplained": 0.4151865197,
    "Mask": "combined",
    "Method": "aCompCor",
    "Retained": true,
    "SingularValue": 39.6411349991,
    "VarianceExplained": 0.0053135172
  },
  "a_comp_cor_52": {
    "CumulativeVarianceExplained": 0.4204456191,
    "Mask": "combined",
    "Method": "aCompCor",
    "Retained": true,
    "SingularValue": 39.437622567,
    "VarianceExplained": 0.0052590995
  },
  "a_comp_cor_53": {
    "CumulativeVarianceExplained": 0.4256637194,
    "Mask": "combined",
    "Method": "aCompCor",
    "Retained": true,
    "SingularValue": 39.283596781,
    "VarianceExplained": 0.0052181003
  },
  "a_comp_cor_54": {
    "CumulativeVarianceExplained": 0.430875489,
    "Mask": "combined",
    "Method": "aCompCor",
    "Retained": true,
    "SingularValue": 39.2597599845,
    "VarianceExplained": 0.0052117696
  },
  "a_comp_cor_55": {
    "CumulativeVarianceExplained": 0.4360526706,
    "Mask": "combined",
    "Method": "aCompCor",
    "Retained": true,
    "SingularValue": 39.1292689408,
    "VarianceExplained": 0.0051771816
  },
  "a_comp_cor_56": {
    "CumulativeVarianceExplained": 0.4412128413,
    "Mask": "combined",
    "Method": "aCompCor",
    "Retained": true,
    "SingularValue": 39.0649316381,
    "VarianceExplained": 0.0051601707
  },
  "a_comp_cor_57": {
    "CumulativeVarianceExplained": 0.4463397606,
    "Mask": "combined",
    "Method": "aCompCor",
    "Retained": true,
    "SingularValue": 38.9388636295,
    "VarianceExplained": 0.0051269193
  },
  "a_comp_cor_58": {
    "CumulativeVarianceExplained": 0.4514067495,
    "Mask": "combined",
    "Method": "aCompCor",
    "Retained": true,
    "SingularValue": 38.7106097966,
    "VarianceExplained": 0.0050669889
  },
  "a_comp_cor_59": {
    "CumulativeVarianceExplained": 0.4564138447,
    "Mask": "combined",
    "Method": "aCompCor",
    "Retained": true,
    "SingularValue": 38.4811424859,
    "VarianceExplained": 0.0050070952
  },
  "a_comp_cor_60": {
    "CumulativeVarianceExplained": 0.4613866653,
    "Mask": "combined",
    "Method": "aCompCor",
    "Retained": true,
    "SingularValue": 38.3492107342,
    "VarianceExplained": 0.0049728206
  },
  "a_comp_cor_61": {
    "CumulativeVarianceExplained": 0.466330444,
    "Mask": "combined",
    "Method": "aCompCor",
    "Retained": true,
    "SingularValue": 38.2370647565,
    "VarianceExplained": 0.0049437787
  },
  "a_comp_cor_62": {
    "CumulativeVarianceExplained": 0.471237618,
    "Mask": "combined",
    "Method": "aCompCor",
    "Retained": true,
    "SingularValue": 38.0952442184,
    "VarianceExplained": 0.004907174
  },
  "a_comp_cor_63": {
    "CumulativeVarianceExplained": 0.4761291942,
    "Mask": "combined",
    "Method": "aCompCor",
    "Retained": true,
    "SingularValue": 38.0346519411,
    "VarianceExplained": 0.0048915762
  },
  "a_comp_cor_64": {
    "CumulativeVarianceExplained": 0.4809842976,
    "Mask": "combined",
    "Method": "aCompCor",
    "Retained": true,
    "SingularValue": 37.8925885986,
    "VarianceExplained": 0.0048551034
  },
  "a_comp_cor_65": {
    "CumulativeVarianceExplained": 0.4857964523,
    "Mask": "combined",
    "Method": "aCompCor",
    "Retained": true,
    "SingularValue": 37.7246157254,
    "VarianceExplained": 0.0048121547
  },
  "a_comp_cor_66": {
    "CumulativeVarianceExplained": 0.4905877459,
    "Mask": "combined",
    "Method": "aCompCor",
    "Retained": true,
    "SingularValue": 37.6427573175,
    "VarianceExplained": 0.0047912936
  },
  "a_comp_cor_67": {
    "CumulativeVarianceExplained": 0.4953192917,
    "Mask": "combined",
    "Method": "aCompCor",
    "Retained": true,
    "SingularValue": 37.4073166034,
    "VarianceExplained": 0.0047315457
  },
  "a_comp_cor_68": {
    "CumulativeVarianceExplained": 0.5000347134,
    "Mask": "combined",
    "Method": "aCompCor",
    "Retained": true,
    "SingularValue": 37.3435244355,
    "VarianceExplained": 0.0047154217
  },
  "c_comp_cor_00": {
    "CumulativeVarianceExplained": 0.2497200879,
    "Mask": "CSF",
    "Method": "aCompCor",
    "Retained": true,
    "SingularValue": 330.3122802495,
    "VarianceExplained": 0.2497200879
  },
  "c_comp_cor_01": {
    "CumulativeVarianceExplained": 0.3018135408,
    "Mask": "CSF",
    "Method": "aCompCor",
    "Retained": true,
    "SingularValue": 150.8653667133,
    "VarianceExplained": 0.0520934529
  },
  "c_comp_cor_02": {
    "CumulativeVarianceExplained": 0.3466357479,
    "Mask": "CSF",
    "Method": "aCompCor",
    "Retained": true,
    "SingularValue": 139.9408796436,
    "VarianceExplained": 0.0448222071
  },
  "c_comp_cor_03": {
    "CumulativeVarianceExplained": 0.3826227742,
    "Mask": "CSF",
    "Method": "aCompCor",
    "Retained": true,
    "SingularValue": 125.392326771,
    "VarianceExplained": 0.0359870263
  },
  "c_comp_cor_04": {
    "CumulativeVarianceExplained": 0.4099805671,
    "Mask": "CSF",
    "Method": "aCompCor",
    "Retained": true,
    "SingularValue": 109.3297888046,
    "VarianceExplained": 0.0273577929
  },
  "c_comp_cor_05": {
    "CumulativeVarianceExplained": 0.4299828345,
    "Mask": "CSF",
    "Method": "aCompCor",
    "Retained": true,
    "SingularValue": 93.4840662637,
    "VarianceExplained": 0.0200022674
  },
  "c_comp_cor_06": {
    "CumulativeVarianceExplained": 0.448232734,
    "Mask": "CSF",
    "Method": "aCompCor",
    "Retained": true,
    "SingularValue": 89.2952216255,
    "VarianceExplained": 0.0182498995
  },
  "c_comp_cor_07": {
    "CumulativeVarianceExplained": 0.4653770549,
    "Mask": "CSF",
    "Method": "aCompCor",
    "Retained": true,
    "SingularValue": 86.5482168154,
    "VarianceExplained": 0.0171443209
  },
  "c_comp_cor_08": {
    "CumulativeVarianceExplained": 0.4805209589,
    "Mask": "CSF",
    "Method": "aCompCor",
    "Retained": true,
    "SingularValue": 81.3423853082,
    "VarianceExplained": 0.0151439039
  },
  "c_comp_cor_09": {
    "CumulativeVarianceExplained": 0.4931286426,
    "Mask": "CSF",
    "Method": "aCompCor",
    "Retained": true,
    "SingularValue": 74.219091593,
    "VarianceExplained": 0.0126076838
  },
  "c_comp_cor_10": {
    "CumulativeVarianceExplained": 0.5046249294,
    "Mask": "CSF",
    "Method": "aCompCor",
    "Retained": true,
    "SingularValue": 70.8723403095,
    "VarianceExplained": 0.0114962867
  },
  "dropped_0": {
    "CumulativeVarianceExplained": 0.2562321942,
    "Mask": "Edge",
    "Method": "EdgeRegressor",
    "Retained": false,
    "SingularValue": 113.8809401552,
    "VarianceExplained": 0.0040807128
  },
  "dropped_1": {
    "CumulativeVarianceExplained": 0.2602948428,
    "Mask": "Edge",
    "Method": "EdgeRegressor",
    "Retained": false,
    "SingularValue": 113.6285999302,
    "VarianceExplained": 0.0040626486
  },
  "dropped_10": {
    "CumulativeVarianceExplained": 0.2959949198,
    "Mask": "Edge",
    "Method": "EdgeRegressor",
    "Retained": false,
    "SingularValue": 111.3546219641,
    "VarianceExplained": 0.0039016692
  },
  "dropped_100": {
    "CumulativeVarianceExplained": 0.6081485321,
    "Mask": "Edge",
    "Method": "EdgeRegressor",
    "Retained": false,
    "SingularValue": 99.9249091198,
    "VarianceExplained": 0.0031418212
  },
  "dropped_101": {
    "CumulativeVarianceExplained": 0.6112869718,
    "Mask": "Edge",
    "Method": "EdgeRegressor",
    "Retained": false,
    "SingularValue": 99.8711209352,
    "VarianceExplained": 0.0031384397
  },
  "dropped_102": {
    "CumulativeVarianceExplained": 0.6144170978,
    "Mask": "Edge",
    "Method": "EdgeRegressor",
    "Retained": false,
    "SingularValue": 99.7387528169,
    "VarianceExplained": 0.0031301259
  },
  "dropped_103": {
    "CumulativeVarianceExplained": 0.6175402603,
    "Mask": "Edge",
    "Method": "EdgeRegressor",
    "Retained": false,
    "SingularValue": 99.6277492419,
    "VarianceExplained": 0.0031231625
  },
  "dropped_104": {
    "CumulativeVarianceExplained": 0.620654136,
    "Mask": "Edge",
    "Method": "EdgeRegressor",
    "Retained": false,
    "SingularValue": 99.479516682,
    "VarianceExplained": 0.0031138757
  },
  "dropped_105": {
    "CumulativeVarianceExplained": 0.6237637871,
    "Mask": "Edge",
    "Method": "EdgeRegressor",
    "Retained": false,
    "SingularValue": 99.4120107009,
    "VarianceExplained": 0.0031096511
  },
  "dropped_106": {
    "CumulativeVarianceExplained": 0.6268676707,
    "Mask": "Edge",
    "Method": "EdgeRegressor",
    "Retained": false,
    "SingularValue": 99.3197777576,
    "VarianceExplained": 0.0031038836
  },
  "dropped_107": {
    "CumulativeVarianceExplained": 0.6299648724,
    "Mask": "Edge",
    "Method": "EdgeRegressor",
    "Retained": false,
    "SingularValue": 99.2128155673,
    "VarianceExplained": 0.0030972017
  },
  "dropped_108": {
    "CumulativeVarianceExplained": 0.6330579009,
    "Mask": "Edge",
    "Method": "EdgeRegressor",
    "Retained": false,
    "SingularValue": 99.1459514439,
    "VarianceExplained": 0.0030930284
  },
  "dropped_109": {
    "CumulativeVarianceExplained": 0.636145827,
    "Mask": "Edge",
    "Method": "EdgeRegressor",
    "Retained": false,
    "SingularValue": 99.0641418057,
    "VarianceExplained": 0.0030879262
  },
  "dropped_11": {
    "CumulativeVarianceExplained": 0.2998849031,
    "Mask": "Edge",
    "Method": "EdgeRegressor",
    "Retained": false,
    "SingularValue": 111.187738243,
    "VarianceExplained": 0.0038899833
  },
  "dropped_110": {
    "CumulativeVarianceExplained": 0.6392275074,
    "Mask": "Edge",
    "Method": "EdgeRegressor",
    "Retained": false,
    "SingularValue": 98.9639048242,
    "VarianceExplained": 0.0030816804
  },
  "dropped_111": {
    "CumulativeVarianceExplained": 0.6422984396,
    "Mask": "Edge",
    "Method": "EdgeRegressor",
    "Retained": false,
    "SingularValue": 98.7911736626,
    "VarianceExplained": 0.0030709322
  },
  "dropped_112": {
    "CumulativeVarianceExplained": 0.6453567183,
    "Mask": "Edge",
    "Method": "EdgeRegressor",
    "Retained": false,
    "SingularValue": 98.5874316234,
    "VarianceExplained": 0.0030582786
  },
  "dropped_113": {
    "CumulativeVarianceExplained": 0.6484133213,
    "Mask": "Edge",
    "Method": "EdgeRegressor",
    "Retained": false,
    "SingularValue": 98.5604196608,
    "VarianceExplained": 0.003056603
  },
  "dropped_114": {
    "CumulativeVarianceExplained": 0.6514669243,
    "Mask": "Edge",
    "Method": "EdgeRegressor",
    "Retained": false,
    "SingularValue": 98.5120404903,
    "VarianceExplained": 0.003053603
  },
  "dropped_115": {
    "CumulativeVarianceExplained": 0.6545119951,
    "Mask": "Edge",
    "Method": "EdgeRegressor",
    "Retained": false,
    "SingularValue": 98.3743171497,
    "VarianceExplained": 0.0030450709
  },
  "dropped_116": {
    "CumulativeVarianceExplained": 0.6575550352,
    "Mask": "Edge",
    "Method": "EdgeRegressor",
    "Retained": false,
    "SingularValue": 98.3415072716,
    "VarianceExplained": 0.00304304
  },
  "dropped_117": {
    "CumulativeVarianceExplained": 0.6605928594,
    "Mask": "Edge",
    "Method": "EdgeRegressor",
    "Retained": false,
    "SingularValue": 98.257191576,
    "VarianceExplained": 0.0030378242
  },
  "dropped_118": {
    "CumulativeVarianceExplained": 0.6636142954,
    "Mask": "Edge",
    "Method": "EdgeRegressor",
    "Retained": false,
    "SingularValue": 97.9917977397,
    "VarianceExplained": 0.003021436
  },
  "dropped_119": {
    "CumulativeVarianceExplained": 0.6666343271,
    "Mask": "Edge",
    "Method": "EdgeRegressor",
    "Retained": false,
    "SingularValue": 97.9690244138,
    "VarianceExplained": 0.0030200318
  },
  "dropped_12": {
    "CumulativeVarianceExplained": 0.3037638525,
    "Mask": "Edge",
    "Method": "EdgeRegressor",
    "Retained": false,
    "SingularValue": 111.0299345695,
    "VarianceExplained": 0.0038789494
  },
  "dropped_120": {
    "CumulativeVarianceExplained": 0.6696462221,
    "Mask": "Edge",
    "Method": "EdgeRegressor",
    "Retained": false,
    "SingularValue": 97.8369570045,
    "VarianceExplained": 0.0030118949
  },
  "dropped_121": {
    "CumulativeVarianceExplained": 0.6726529661,
    "Mask": "Edge",
    "Method": "EdgeRegressor",
    "Retained": false,
    "SingularValue": 97.753262175,
    "VarianceExplained": 0.0030067441
  },
  "dropped_122": {
    "CumulativeVarianceExplained": 0.6756518281,
    "Mask": "Edge",
    "Method": "EdgeRegressor",
    "Retained": false,
    "SingularValue": 97.6250493929,
    "VarianceExplained": 0.002998862
  },
  "dropped_123": {
    "CumulativeVarianceExplained": 0.6786461908,
    "Mask": "Edge",
    "Method": "EdgeRegressor",
    "Retained": false,
    "SingularValue": 97.5517864823,
    "VarianceExplained": 0.0029943627
  },
  "dropped_124": {
    "CumulativeVarianceExplained": 0.6816344355,
    "Mask": "Edge",
    "Method": "EdgeRegressor",
    "Retained": false,
    "SingularValue": 97.4520787847,
    "VarianceExplained": 0.0029882447
  },
  "dropped_125": {
    "CumulativeVarianceExplained": 0.6846147019,
    "Mask": "Edge",
    "Method": "EdgeRegressor",
    "Retained": false,
    "SingularValue": 97.321897806,
    "VarianceExplained": 0.0029802664
  },
  "dropped_126": {
    "CumulativeVarianceExplained": 0.6875923928,
    "Mask": "Edge",
    "Method": "EdgeRegressor",
    "Retained": false,
    "SingularValue": 97.2798375286,
    "VarianceExplained": 0.0029776909
  },
  "dropped_127": {
    "CumulativeVarianceExplained": 0.6905645925,
    "Mask": "Edge",
    "Method": "EdgeRegressor",
    "Retained": false,
    "SingularValue": 97.1900979957,
    "VarianceExplained": 0.0029721997
  },
  "dropped_128": {
    "CumulativeVarianceExplained": 0.6935297579,
    "Mask": "Edge",
    "Method": "EdgeRegressor",
    "Retained": false,
    "SingularValue": 97.0750197877,
    "VarianceExplained": 0.0029651654
  },
  "dropped_129": {
    "CumulativeVarianceExplained": 0.6964929125,
    "Mask": "Edge",
    "Method": "EdgeRegressor",
    "Retained": false,
    "SingularValue": 97.0421000489,
    "VarianceExplained": 0.0029631546
  },
  "dropped_13": {
    "CumulativeVarianceExplained": 0.3076311298,
    "Mask": "Edge",
    "Method": "EdgeRegressor",
    "Retained": false,
    "SingularValue": 110.8627600831,
    "VarianceExplained": 0.0038672773
  },
  "dropped_130": {
    "CumulativeVarianceExplained": 0.6994434475,
    "Mask": "Edge",
    "Method": "EdgeRegressor",
    "Retained": false,
    "SingularValue": 96.8352346988,
    "VarianceExplained": 0.002950535
  },
  "dropped_131": {
    "CumulativeVarianceExplained": 0.7023888067,
    "Mask": "Edge",
    "Method": "EdgeRegressor",
    "Retained": false,
    "SingularValue": 96.750264721,
    "VarianceExplained": 0.0029453592
  },
  "dropped_132": {
    "CumulativeVarianceExplained": 0.7053306538,
    "Mask": "Edge",
    "Method": "EdgeRegressor",
    "Retained": false,
    "SingularValue": 96.6925637338,
    "VarianceExplained": 0.0029418471
  },
  "dropped_133": {
    "CumulativeVarianceExplained": 0.7082699168,
    "Mask": "Edge",
    "Method": "EdgeRegressor",
    "Retained": false,
    "SingularValue": 96.6500873707,
    "VarianceExplained": 0.002939263
  },
  "dropped_134": {
    "CumulativeVarianceExplained": 0.7112017875,
    "Mask": "Edge",
    "Method": "EdgeRegressor",
    "Retained": false,
    "SingularValue": 96.5284728435,
    "VarianceExplained": 0.0029318707
  },
  "dropped_135": {
    "CumulativeVarianceExplained": 0.7141171565,
    "Mask": "Edge",
    "Method": "EdgeRegressor",
    "Retained": false,
    "SingularValue": 96.2564393524,
    "VarianceExplained": 0.002915369
  },
  "dropped_136": {
    "CumulativeVarianceExplained": 0.7170308373,
    "Mask": "Edge",
    "Method": "EdgeRegressor",
    "Retained": false,
    "SingularValue": 96.2285656809,
    "VarianceExplained": 0.0029136808
  },
  "dropped_137": {
    "CumulativeVarianceExplained": 0.7199379398,
    "Mask": "Edge",
    "Method": "EdgeRegressor",
    "Retained": false,
    "SingularValue": 96.1198760392,
    "VarianceExplained": 0.0029071025
  },
  "dropped_138": {
    "CumulativeVarianceExplained": 0.7228406769,
    "Mask": "Edge",
    "Method": "EdgeRegressor",
    "Retained": false,
    "SingularValue": 96.0476803404,
    "VarianceExplained": 0.0029027371
  },
  "dropped_139": {
    "CumulativeVarianceExplained": 0.7257372426,
    "Mask": "Edge",
    "Method": "EdgeRegressor",
    "Retained": false,
    "SingularValue": 95.9455239419,
    "VarianceExplained": 0.0028965657
  },
  "dropped_14": {
    "CumulativeVarianceExplained": 0.3114861948,
    "Mask": "Edge",
    "Method": "EdgeRegressor",
    "Retained": false,
    "SingularValue": 110.687576814,
    "VarianceExplained": 0.003855065
  },
  "dropped_140": {
    "CumulativeVarianceExplained": 0.7286229461,
    "Mask": "Edge",
    "Method": "EdgeRegressor",
    "Retained": false,
    "SingularValue": 95.7654565325,
    "VarianceExplained": 0.0028857035
  },
  "dropped_141": {
    "CumulativeVarianceExplained": 0.7315041483,
    "Mask": "Edge",
    "Method": "EdgeRegressor",
    "Retained": false,
    "SingularValue": 95.6907358594,
    "VarianceExplained": 0.0028812022
  },
  "dropped_142": {
    "CumulativeVarianceExplained": 0.7343752326,
    "Mask": "Edge",
    "Method": "EdgeRegressor",
    "Retained": false,
    "SingularValue": 95.5225709106,
    "VarianceExplained": 0.0028710843
  },
  "dropped_143": {
    "CumulativeVarianceExplained": 0.737242488,
    "Mask": "Edge",
    "Method": "EdgeRegressor",
    "Retained": false,
    "SingularValue": 95.4588528871,
    "VarianceExplained": 0.0028672553
  },
  "dropped_144": {
    "CumulativeVarianceExplained": 0.740108334,
    "Mask": "Edge",
    "Method": "EdgeRegressor",
    "Retained": false,
    "SingularValue": 95.4353902381,
    "VarianceExplained": 0.002865846
  },
  "dropped_145": {
    "CumulativeVarianceExplained": 0.7429603748,
    "Mask": "Edge",
    "Method": "EdgeRegressor",
    "Retained": false,
    "SingularValue": 95.2052495026,
    "VarianceExplained": 0.0028520408
  },
  "dropped_146": {
    "CumulativeVarianceExplained": 0.7458089877,
    "Mask": "Edge",
    "Method": "EdgeRegressor",
    "Retained": false,
    "SingularValue": 95.1480187069,
    "VarianceExplained": 0.0028486129
  },
  "dropped_147": {
    "CumulativeVarianceExplained": 0.7486503509,
    "Mask": "Edge",
    "Method": "EdgeRegressor",
    "Retained": false,
    "SingularValue": 95.0268640829,
    "VarianceExplained": 0.0028413631
  },
  "dropped_148": {
    "CumulativeVarianceExplained": 0.751487509,
    "Mask": "Edge",
    "Method": "EdgeRegressor",
    "Retained": false,
    "SingularValue": 94.956522468,
    "VarianceExplained": 0.0028371582
  },
  "dropped_149": {
    "CumulativeVarianceExplained": 0.754322762,
    "Mask": "Edge",
    "Method": "EdgeRegressor",
    "Retained": false,
    "SingularValue": 94.9246347607,
    "VarianceExplained": 0.002835253
  },
  "dropped_15": {
    "CumulativeVarianceExplained": 0.3153234463,
    "Mask": "Edge",
    "Method": "EdgeRegressor",
    "Retained": false,
    "SingularValue": 110.4315486145,
    "VarianceExplained": 0.0038372515
  },
  "dropped_150": {
    "CumulativeVarianceExplained": 0.7571479526,
    "Mask": "Edge",
    "Method": "EdgeRegressor",
    "Retained": false,
    "SingularValue": 94.7560399924,
    "VarianceExplained": 0.0028251906
  },
  "dropped_151": {
    "CumulativeVarianceExplained": 0.75997068,
    "Mask": "Edge",
    "Method": "EdgeRegressor",
    "Retained": false,
    "SingularValue": 94.7147246125,
    "VarianceExplained": 0.0028227274
  },
  "dropped_152": {
    "CumulativeVarianceExplained": 0.7627828641,
    "Mask": "Edge",
    "Method": "EdgeRegressor",
    "Retained": false,
    "SingularValue": 94.537671721,
    "VarianceExplained": 0.0028121841
  },
  "dropped_153": {
    "CumulativeVarianceExplained": 0.7655937047,
    "Mask": "Edge",
    "Method": "EdgeRegressor",
    "Retained": false,
    "SingularValue": 94.515085972,
    "VarianceExplained": 0.0028108406
  },
  "dropped_154": {
    "CumulativeVarianceExplained": 0.7684006305,
    "Mask": "Edge",
    "Method": "EdgeRegressor",
    "Retained": false,
    "SingularValue": 94.4492460597,
    "VarianceExplained": 0.0028069258
  },
  "dropped_155": {
    "CumulativeVarianceExplained": 0.7712026541,
    "Mask": "Edge",
    "Method": "EdgeRegressor",
    "Retained": false,
    "SingularValue": 94.3667329885,
    "VarianceExplained": 0.0028020236
  },
  "dropped_156": {
    "CumulativeVarianceExplained": 0.7739902137,
    "Mask": "Edge",
    "Method": "EdgeRegressor",
    "Retained": false,
    "SingularValue": 94.1228577123,
    "VarianceExplained": 0.0027875596
  },
  "dropped_157": {
    "CumulativeVarianceExplained": 0.7767755997,
    "Mask": "Edge",
    "Method": "EdgeRegressor",
    "Retained": false,
    "SingularValue": 94.0861561903,
    "VarianceExplained": 0.0027853861
  },
  "dropped_158": {
    "CumulativeVarianceExplained": 0.7795505566,
    "Mask": "Edge",
    "Method": "EdgeRegressor",
    "Retained": false,
    "SingularValue": 93.9098501785,
    "VarianceExplained": 0.0027749569
  },
  "dropped_159": {
    "CumulativeVarianceExplained": 0.7823199678,
    "Mask": "Edge",
    "Method": "EdgeRegressor",
    "Retained": false,
    "SingularValue": 93.8159649833,
    "VarianceExplained": 0.0027694112
  },
  "dropped_16": {
    "CumulativeVarianceExplained": 0.3191406783,
    "Mask": "Edge",
    "Method": "EdgeRegressor",
    "Retained": false,
    "SingularValue": 110.143101658,
    "VarianceExplained": 0.0038172319
  },
  "dropped_160": {
    "CumulativeVarianceExplained": 0.7850854358,
    "Mask": "Edge",
    "Method": "EdgeRegressor",
    "Retained": false,
    "SingularValue": 93.7491521597,
    "VarianceExplained": 0.002765468
  },
  "dropped_161": {
    "CumulativeVarianceExplained": 0.7878481509,
    "Mask": "Edge",
    "Method": "EdgeRegressor",
    "Retained": false,
    "SingularValue": 93.7024779273,
    "VarianceExplained": 0.0027627151
  },
  "dropped_162": {
    "CumulativeVarianceExplained": 0.7905952772,
    "Mask": "Edge",
    "Method": "EdgeRegressor",
    "Retained": false,
    "SingularValue": 93.4377429966,
    "VarianceExplained": 0.0027471263
  },
  "dropped_163": {
    "CumulativeVarianceExplained": 0.7933405875,
    "Mask": "Edge",
    "Method": "EdgeRegressor",
    "Retained": false,
    "SingularValue": 93.4068552211,
    "VarianceExplained": 0.0027453103
  },
  "dropped_164": {
    "CumulativeVarianceExplained": 0.7960793973,
    "Mask": "Edge",
    "Method": "EdgeRegressor",
    "Retained": false,
    "SingularValue": 93.2962019185,
    "VarianceExplained": 0.0027388098
  },
  "dropped_165": {
    "CumulativeVarianceExplained": 0.7988171668,
    "Mask": "Edge",
    "Method": "EdgeRegressor",
    "Retained": false,
    "SingularValue": 93.2784810402,
    "VarianceExplained": 0.0027377695
  },
  "dropped_166": {
    "CumulativeVarianceExplained": 0.8015439786,
    "Mask": "Edge",
    "Method": "EdgeRegressor",
    "Retained": false,
    "SingularValue": 93.0916252888,
    "VarianceExplained": 0.0027268118
  },
  "dropped_167": {
    "CumulativeVarianceExplained": 0.8042663207,
    "Mask": "Edge",
    "Method": "EdgeRegressor",
    "Retained": false,
    "SingularValue": 93.0152965251,
    "VarianceExplained": 0.0027223421
  },
  "dropped_168": {
    "CumulativeVarianceExplained": 0.8069846503,
    "Mask": "Edge",
    "Method": "EdgeRegressor",
    "Retained": false,
    "SingularValue": 92.9467232412,
    "VarianceExplained": 0.0027183296
  },
  "dropped_169": {
    "CumulativeVarianceExplained": 0.8096883827,
    "Mask": "Edge",
    "Method": "EdgeRegressor",
    "Retained": false,
    "SingularValue": 92.696829997,
    "VarianceExplained": 0.0027037324
  },
  "dropped_17": {
    "CumulativeVarianceExplained": 0.3229440447,
    "Mask": "Edge",
    "Method": "EdgeRegressor",
    "Retained": false,
    "SingularValue": 109.9428804223,
    "VarianceExplained": 0.0038033664
  },
  "dropped_170": {
    "CumulativeVarianceExplained": 0.8123868431,
    "Mask": "Edge",
    "Method": "EdgeRegressor",
    "Retained": false,
    "SingularValue": 92.6064102839,
    "VarianceExplained": 0.0026984604
  },
  "dropped_171": {
    "CumulativeVarianceExplained": 0.8150836515,
    "Mask": "Edge",
    "Method": "EdgeRegressor",
    "Retained": false,
    "SingularValue": 92.5780599262,
    "VarianceExplained": 0.0026968084
  },
  "dropped_172": {
    "CumulativeVarianceExplained": 0.8177706365,
    "Mask": "Edge",
    "Method": "EdgeRegressor",
    "Retained": false,
    "SingularValue": 92.4092938785,
    "VarianceExplained": 0.002686985
  },
  "dropped_173": {
    "CumulativeVarianceExplained": 0.8204559874,
    "Mask": "Edge",
    "Method": "EdgeRegressor",
    "Retained": false,
    "SingularValue": 92.3811883095,
    "VarianceExplained": 0.0026853508
  },
  "dropped_174": {
    "CumulativeVarianceExplained": 0.823137826,
    "Mask": "Edge",
    "Method": "EdgeRegressor",
    "Retained": false,
    "SingularValue": 92.3207551181,
    "VarianceExplained": 0.0026818386
  },
  "dropped_175": {
    "CumulativeVarianceExplained": 0.8258041608,
    "Mask": "Edge",
    "Method": "EdgeRegressor",
    "Retained": false,
    "SingularValue": 92.0535131382,
    "VarianceExplained": 0.0026663348
  },
  "dropped_176": {
    "CumulativeVarianceExplained": 0.8284689623,
    "Mask": "Edge",
    "Method": "EdgeRegressor",
    "Retained": false,
    "SingularValue": 92.0270409266,
    "VarianceExplained": 0.0026648015
  },
  "dropped_177": {
    "CumulativeVarianceExplained": 0.8311294336,
    "Mask": "Edge",
    "Method": "EdgeRegressor",
    "Retained": false,
    "SingularValue": 91.9522411431,
    "VarianceExplained": 0.0026604713
  },
  "dropped_178": {
    "CumulativeVarianceExplained": 0.8337862504,
    "Mask": "Edge",
    "Method": "EdgeRegressor",
    "Retained": false,
    "SingularValue": 91.8890641229,
    "VarianceExplained": 0.0026568168
  },
  "dropped_179": {
    "CumulativeVarianceExplained": 0.8364276975,
    "Mask": "Edge",
    "Method": "EdgeRegressor",
    "Retained": false,
    "SingularValue": 91.6228915993,
    "VarianceExplained": 0.0026414472
  },
  "dropped_18": {
    "CumulativeVarianceExplained": 0.3267366999,
    "Mask": "Edge",
    "Method": "EdgeRegressor",
    "Retained": false,
    "SingularValue": 109.7879578902,
    "VarianceExplained": 0.0037926552
  },
  "dropped_180": {
    "CumulativeVarianceExplained": 0.839065524,
    "Mask": "Edge",
    "Method": "EdgeRegressor",
    "Retained": false,
    "SingularValue": 91.5600747723,
    "VarianceExplained": 0.0026378265
  },
  "dropped_181": {
    "CumulativeVarianceExplained": 0.8416957291,
    "Mask": "Edge",
    "Method": "EdgeRegressor",
    "Retained": false,
    "SingularValue": 91.4277079032,
    "VarianceExplained": 0.0026302051
  },
  "dropped_182": {
    "CumulativeVarianceExplained": 0.8443225722,
    "Mask": "Edge",
    "Method": "EdgeRegressor",
    "Retained": false,
    "SingularValue": 91.3692573203,
    "VarianceExplained": 0.0026268431
  },
  "dropped_183": {
    "CumulativeVarianceExplained": 0.8469436922,
    "Mask": "Edge",
    "Method": "EdgeRegressor",
    "Retained": false,
    "SingularValue": 91.2696692872,
    "VarianceExplained": 0.00262112
  },
  "dropped_184": {
    "CumulativeVarianceExplained": 0.8495570448,
    "Mask": "Edge",
    "Method": "EdgeRegressor",
    "Retained": false,
    "SingularValue": 91.1343373354,
    "VarianceExplained": 0.0026133527
  },
  "dropped_185": {
    "CumulativeVarianceExplained": 0.8521638747,
    "Mask": "Edge",
    "Method": "EdgeRegressor",
    "Retained": false,
    "SingularValue": 91.0205326086,
    "VarianceExplained": 0.0026068299
  },
  "dropped_186": {
    "CumulativeVarianceExplained": 0.8547645441,
    "Mask": "Edge",
    "Method": "EdgeRegressor",
    "Retained": false,
    "SingularValue": 90.9129180676,
    "VarianceExplained": 0.0026006694
  },
  "dropped_187": {
    "CumulativeVarianceExplained": 0.8573630068,
    "Mask": "Edge",
    "Method": "EdgeRegressor",
    "Retained": false,
    "SingularValue": 90.8743400569,
    "VarianceExplained": 0.0025984627
  },
  "dropped_188": {
    "CumulativeVarianceExplained": 0.8599591981,
    "Mask": "Edge",
    "Method": "EdgeRegressor",
    "Retained": false,
    "SingularValue": 90.8346142156,
    "VarianceExplained": 0.0025961913
  },
  "dropped_189": {
    "CumulativeVarianceExplained": 0.862545884,
    "Mask": "Edge",
    "Method": "EdgeRegressor",
    "Retained": false,
    "SingularValue": 90.668175399,
    "VarianceExplained": 0.0025866859
  },
  "dropped_19": {
    "CumulativeVarianceExplained": 0.3305185489,
    "Mask": "Edge",
    "Method": "EdgeRegressor",
    "Retained": false,
    "SingularValue": 109.6314409061,
    "VarianceExplained": 0.003781849
  },
  "dropped_190": {
    "CumulativeVarianceExplained": 0.8651262092,
    "Mask": "Edge",
    "Method": "EdgeRegressor",
    "Retained": false,
    "SingularValue": 90.5566284617,
    "VarianceExplained": 0.0025803251
  },
  "dropped_191": {
    "CumulativeVarianceExplained": 0.8676973832,
    "Mask": "Edge",
    "Method": "EdgeRegressor",
    "Retained": false,
    "SingularValue": 90.3959075575,
    "VarianceExplained": 0.0025711741
  },
  "dropped_192": {
    "CumulativeVarianceExplained": 0.8702668648,
    "Mask": "Edge",
    "Method": "EdgeRegressor",
    "Retained": false,
    "SingularValue": 90.3661500258,
    "VarianceExplained": 0.0025694816
  },
  "dropped_193": {
    "CumulativeVarianceExplained": 0.8728285646,
    "Mask": "Edge",
    "Method": "EdgeRegressor",
    "Retained": false,
    "SingularValue": 90.2292069737,
    "VarianceExplained": 0.0025616997
  },
  "dropped_194": {
    "CumulativeVarianceExplained": 0.8753864969,
    "Mask": "Edge",
    "Method": "EdgeRegressor",
    "Retained": false,
    "SingularValue": 90.1628335751,
    "VarianceExplained": 0.0025579323
  },
  "dropped_195": {
    "CumulativeVarianceExplained": 0.8779346463,
    "Mask": "Edge",
    "Method": "EdgeRegressor",
    "Retained": false,
    "SingularValue": 89.9902535525,
    "VarianceExplained": 0.0025481494
  },
  "dropped_196": {
    "CumulativeVarianceExplained": 0.8804761499,
    "Mask": "Edge",
    "Method": "EdgeRegressor",
    "Retained": false,
    "SingularValue": 89.8728244352,
    "VarianceExplained": 0.0025415036
  },
  "dropped_197": {
    "CumulativeVarianceExplained": 0.8830129676,
    "Mask": "Edge",
    "Method": "EdgeRegressor",
    "Retained": false,
    "SingularValue": 89.789934125,
    "VarianceExplained": 0.0025368177
  },
  "dropped_198": {
    "CumulativeVarianceExplained": 0.8855477029,
    "Mask": "Edge",
    "Method": "EdgeRegressor",
    "Retained": false,
    "SingularValue": 89.7530751704,
    "VarianceExplained": 0.0025347353
  },
  "dropped_199": {
    "CumulativeVarianceExplained": 0.8880783191,
    "Mask": "Edge",
    "Method": "EdgeRegressor",
    "Retained": false,
    "SingularValue": 89.6801181697,
    "VarianceExplained": 0.0025306162
  },
  "dropped_2": {
    "CumulativeVarianceExplained": 0.264328199,
    "Mask": "Edge",
    "Method": "EdgeRegressor",
    "Retained": false,
    "SingularValue": 113.2182175393,
    "VarianceExplained": 0.0040333561
  },
  "dropped_20": {
    "CumulativeVarianceExplained": 0.3342854145,
    "Mask": "Edge",
    "Method": "EdgeRegressor",
    "Retained": false,
    "SingularValue": 109.4140486897,
    "VarianceExplained": 0.0037668656
  },
  "dropped_200": {
    "CumulativeVarianceExplained": 0.8906022375,
    "Mask": "Edge",
    "Method": "EdgeRegressor",
    "Retained": false,
    "SingularValue": 89.5613603217,
    "VarianceExplained": 0.0025239184
  },
  "dropped_201": {
    "CumulativeVarianceExplained": 0.8931150121,
    "Mask": "Edge",
    "Method": "EdgeRegressor",
    "Retained": false,
    "SingularValue": 89.3634227518,
    "VarianceExplained": 0.0025127746
  },
  "dropped_202": {
    "CumulativeVarianceExplained": 0.8956209116,
    "Mask": "Edge",
    "Method": "EdgeRegressor",
    "Retained": false,
    "SingularValue": 89.2410878824,
    "VarianceExplained": 0.0025058995
  },
  "dropped_203": {
    "CumulativeVarianceExplained": 0.8981164587,
    "Mask": "Edge",
    "Method": "EdgeRegressor",
    "Retained": false,
    "SingularValue": 89.0565578782,
    "VarianceExplained": 0.002495547
  },
  "dropped_204": {
    "CumulativeVarianceExplained": 0.9006054742,
    "Mask": "Edge",
    "Method": "EdgeRegressor",
    "Retained": false,
    "SingularValue": 88.9399403168,
    "VarianceExplained": 0.0024890156
  },
  "dropped_205": {
    "CumulativeVarianceExplained": 0.9030888747,
    "Mask": "Edge",
    "Method": "EdgeRegressor",
    "Retained": false,
    "SingularValue": 88.8395623507,
    "VarianceExplained": 0.0024834005
  },
  "dropped_206": {
    "CumulativeVarianceExplained": 0.9055657196,
    "Mask": "Edge",
    "Method": "EdgeRegressor",
    "Retained": false,
    "SingularValue": 88.7222264566,
    "VarianceExplained": 0.0024768449
  },
  "dropped_207": {
    "CumulativeVarianceExplained": 0.9080389713,
    "Mask": "Edge",
    "Method": "EdgeRegressor",
    "Retained": false,
    "SingularValue": 88.6578478429,
    "VarianceExplained": 0.0024732517
  },
  "dropped_208": {
    "CumulativeVarianceExplained": 0.91050287,
    "Mask": "Edge",
    "Method": "EdgeRegressor",
    "Retained": false,
    "SingularValue": 88.4900521178,
    "VarianceExplained": 0.0024638987
  },
  "dropped_209": {
    "CumulativeVarianceExplained": 0.912957214,
    "Mask": "Edge",
    "Method": "EdgeRegressor",
    "Retained": false,
    "SingularValue": 88.3183086329,
    "VarianceExplained": 0.002454344
  },
  "dropped_21": {
    "CumulativeVarianceExplained": 0.3380466673,
    "Mask": "Edge",
    "Method": "EdgeRegressor",
    "Retained": false,
    "SingularValue": 109.332502691,
    "VarianceExplained": 0.0037612528
  },
  "dropped_210": {
    "CumulativeVarianceExplained": 0.9154089252,
    "Mask": "Edge",
    "Method": "EdgeRegressor",
    "Retained": false,
    "SingularValue": 88.270927278,
    "VarianceExplained": 0.0024517113
  },
  "dropped_211": {
    "CumulativeVarianceExplained": 0.9178510626,
    "Mask": "Edge",
    "Method": "EdgeRegressor",
    "Retained": false,
    "SingularValue": 88.098409631,
    "VarianceExplained": 0.0024421373
  },
  "dropped_212": {
    "CumulativeVarianceExplained": 0.9202883037,
    "Mask": "Edge",
    "Method": "EdgeRegressor",
    "Retained": false,
    "SingularValue": 88.0100509639,
    "VarianceExplained": 0.0024372411
  },
  "dropped_213": {
    "CumulativeVarianceExplained": 0.9227201478,
    "Mask": "Edge",
    "Method": "EdgeRegressor",
    "Retained": false,
    "SingularValue": 87.9125544511,
    "VarianceExplained": 0.0024318442
  },
  "dropped_214": {
    "CumulativeVarianceExplained": 0.9251493907,
    "Mask": "Edge",
    "Method": "EdgeRegressor",
    "Retained": false,
    "SingularValue": 87.8655218403,
    "VarianceExplained": 0.0024292428
  },
  "dropped_215": {
    "CumulativeVarianceExplained": 0.9275734229,
    "Mask": "Edge",
    "Method": "EdgeRegressor",
    "Retained": false,
    "SingularValue": 87.771236979,
    "VarianceExplained": 0.0024240322
  },
  "dropped_216": {
    "CumulativeVarianceExplained": 0.9299861473,
    "Mask": "Edge",
    "Method": "EdgeRegressor",
    "Retained": false,
    "SingularValue": 87.5662774221,
    "VarianceExplained": 0.0024127244
  },
  "dropped_217": {
    "CumulativeVarianceExplained": 0.9323892962,
    "Mask": "Edge",
    "Method": "EdgeRegressor",
    "Retained": false,
    "SingularValue": 87.3923395689,
    "VarianceExplained": 0.0024031489
  },
  "dropped_218": {
    "CumulativeVarianceExplained": 0.9347808066,
    "Mask": "Edge",
    "Method": "EdgeRegressor",
    "Retained": false,
    "SingularValue": 87.1804628988,
    "VarianceExplained": 0.0023915105
  },
  "dropped_219": {
    "CumulativeVarianceExplained": 0.9371673625,
    "Mask": "Edge",
    "Method": "EdgeRegressor",
    "Retained": false,
    "SingularValue": 87.0901084628,
    "VarianceExplained": 0.0023865559
  },
  "dropped_22": {
    "CumulativeVarianceExplained": 0.3418015025,
    "Mask": "Edge",
    "Method": "EdgeRegressor",
    "Retained": false,
    "SingularValue": 109.2391891964,
    "VarianceExplained": 0.0037548352
  },
  "dropped_220": {
    "CumulativeVarianceExplained": 0.9395480558,
    "Mask": "Edge",
    "Method": "EdgeRegressor",
    "Retained": false,
    "SingularValue": 86.9830742973,
    "VarianceExplained": 0.0023806933
  },
  "dropped_221": {
    "CumulativeVarianceExplained": 0.9419271647,
    "Mask": "Edge",
    "Method": "EdgeRegressor",
    "Retained": false,
    "SingularValue": 86.954125193,
    "VarianceExplained": 0.0023791089
  },
  "dropped_222": {
    "CumulativeVarianceExplained": 0.9443006427,
    "Mask": "Edge",
    "Method": "EdgeRegressor",
    "Retained": false,
    "SingularValue": 86.8511609394,
    "VarianceExplained": 0.0023734779
  },
  "dropped_223": {
    "CumulativeVarianceExplained": 0.9466629295,
    "Mask": "Edge",
    "Method": "EdgeRegressor",
    "Retained": false,
    "SingularValue": 86.6461639247,
    "VarianceExplained": 0.0023622868
  },
  "dropped_224": {
    "CumulativeVarianceExplained": 0.9490209119,
    "Mask": "Edge",
    "Method": "EdgeRegressor",
    "Retained": false,
    "SingularValue": 86.5671875501,
    "VarianceExplained": 0.0023579824
  },
  "dropped_225": {
    "CumulativeVarianceExplained": 0.9513616279,
    "Mask": "Edge",
    "Method": "EdgeRegressor",
    "Retained": false,
    "SingularValue": 86.2496591704,
    "VarianceExplained": 0.002340716
  },
  "dropped_226": {
    "CumulativeVarianceExplained": 0.9536987786,
    "Mask": "Edge",
    "Method": "EdgeRegressor",
    "Retained": false,
    "SingularValue": 86.1839481137,
    "VarianceExplained": 0.0023371507
  },
  "dropped_227": {
    "CumulativeVarianceExplained": 0.9560306669,
    "Mask": "Edge",
    "Method": "EdgeRegressor",
    "Retained": false,
    "SingularValue": 86.0868674239,
    "VarianceExplained": 0.0023318884
  },
  "dropped_228": {
    "CumulativeVarianceExplained": 0.9583515481,
    "Mask": "Edge",
    "Method": "EdgeRegressor",
    "Retained": false,
    "SingularValue": 85.88344879,
    "VarianceExplained": 0.0023208811
  },
  "dropped_229": {
    "CumulativeVarianceExplained": 0.9606705817,
    "Mask": "Edge",
    "Method": "EdgeRegressor",
    "Retained": false,
    "SingularValue": 85.8492598942,
    "VarianceExplained": 0.0023190337
  },
  "dropped_23": {
    "CumulativeVarianceExplained": 0.3455442056,
    "Mask": "Edge",
    "Method": "EdgeRegressor",
    "Retained": false,
    "SingularValue": 109.0625680437,
    "VarianceExplained": 0.0037427032
  },
  "dropped_230": {
    "CumulativeVarianceExplained": 0.962971852,
    "Mask": "Edge",
    "Method": "EdgeRegressor",
    "Retained": false,
    "SingularValue": 85.5198323896,
    "VarianceExplained": 0.0023012703
  },
  "dropped_231": {
    "CumulativeVarianceExplained": 0.9652718677,
    "Mask": "Edge",
    "Method": "EdgeRegressor",
    "Retained": false,
    "SingularValue": 85.4965171258,
    "VarianceExplained": 0.0023000157
  },
  "dropped_232": {
    "CumulativeVarianceExplained": 0.9675640261,
    "Mask": "Edge",
    "Method": "EdgeRegressor",
    "Retained": false,
    "SingularValue": 85.3503577615,
    "VarianceExplained": 0.0022921585
  },
  "dropped_233": {
    "CumulativeVarianceExplained": 0.9698434142,
    "Mask": "Edge",
    "Method": "EdgeRegressor",
    "Retained": false,
    "SingularValue": 85.1122684884,
    "VarianceExplained": 0.0022793881
  },
  "dropped_234": {
    "CumulativeVarianceExplained": 0.9721177653,
    "Mask": "Edge",
    "Method": "EdgeRegressor",
    "Retained": false,
    "SingularValue": 85.0181759491,
    "VarianceExplained": 0.0022743511
  },
  "dropped_235": {
    "CumulativeVarianceExplained": 0.9743875098,
    "Mask": "Edge",
    "Method": "EdgeRegressor",
    "Retained": false,
    "SingularValue": 84.9320313966,
    "VarianceExplained": 0.0022697445
  },
  "dropped_236": {
    "CumulativeVarianceExplained": 0.976642112,
    "Mask": "Edge",
    "Method": "EdgeRegressor",
    "Retained": false,
    "SingularValue": 84.6482520717,
    "VarianceExplained": 0.0022546022
  },
  "dropped_237": {
    "CumulativeVarianceExplained": 0.9788890993,
    "Mask": "Edge",
    "Method": "EdgeRegressor",
    "Retained": false,
    "SingularValue": 84.5051809277,
    "VarianceExplained": 0.0022469873
  },
  "dropped_238": {
    "CumulativeVarianceExplained": 0.9811228562,
    "Mask": "Edge",
    "Method": "EdgeRegressor",
    "Retained": false,
    "SingularValue": 84.2560273127,
    "VarianceExplained": 0.0022337569
  },
  "dropped_239": {
    "CumulativeVarianceExplained": 0.9833422324,
    "Mask": "Edge",
    "Method": "EdgeRegressor",
    "Retained": false,
    "SingularValue": 83.9843730759,
    "VarianceExplained": 0.0022193761
  },
  "dropped_24": {
    "CumulativeVarianceExplained": 0.3492733068,
    "Mask": "Edge",
    "Method": "EdgeRegressor",
    "Retained": false,
    "SingularValue": 108.8642059148,
    "VarianceExplained": 0.0037291011
  },
  "dropped_240": {
    "CumulativeVarianceExplained": 0.9855576784,
    "Mask": "Edge",
    "Method": "EdgeRegressor",
    "Retained": false,
    "SingularValue": 83.9099807344,
    "VarianceExplained": 0.0022154461
  },
  "dropped_241": {
    "CumulativeVarianceExplained": 0.9877565008,
    "Mask": "Edge",
    "Method": "EdgeRegressor",
    "Retained": false,
    "SingularValue": 83.5945758489,
    "VarianceExplained": 0.0021988223
  },
  "dropped_242": {
    "CumulativeVarianceExplained": 0.9899502838,
    "Mask": "Edge",
    "Method": "EdgeRegressor",
    "Retained": false,
    "SingularValue": 83.4987276089,
    "VarianceExplained": 0.002193783
  },
  "dropped_243": {
    "CumulativeVarianceExplained": 0.9921349044,
    "Mask": "Edge",
    "Method": "EdgeRegressor",
    "Retained": false,
    "SingularValue": 83.3241796238,
    "VarianceExplained": 0.0021846207
  },
  "dropped_244": {
    "CumulativeVarianceExplained": 0.9943082453,
    "Mask": "Edge",
    "Method": "EdgeRegressor",
    "Retained": false,
    "SingularValue": 83.1087892083,
    "VarianceExplained": 0.0021733409
  },
  "dropped_245": {
    "CumulativeVarianceExplained": 0.9964304499,
    "Mask": "Edge",
    "Method": "EdgeRegressor",
    "Retained": false,
    "SingularValue": 82.1252390275,
    "VarianceExplained": 0.0021222045
  },
  "dropped_246": {
    "CumulativeVarianceExplained": 0.9983740063,
    "Mask": "Edge",
    "Method": "EdgeRegressor",
    "Retained": false,
    "SingularValue": 78.5925909026,
    "VarianceExplained": 0.0019435564
  },
  "dropped_247": {
    "CumulativeVarianceExplained": 1.0,
    "Mask": "Edge",
    "Method": "EdgeRegressor",
    "Retained": false,
    "SingularValue": 71.8856916096,
    "VarianceExplained": 0.0016259937
  },
  "dropped_248": {
    "CumulativeVarianceExplained": 1.0,
    "Mask": "Edge",
    "Method": "EdgeRegressor",
    "Retained": false,
    "SingularValue": 0.0,
    "VarianceExplained": 0.0
  },
  "dropped_249": {
    "CumulativeVarianceExplained": 1.0,
    "Mask": "Edge",
    "Method": "EdgeRegressor",
    "Retained": false,
    "SingularValue": 0.0,
    "VarianceExplained": 0.0
  },
  "dropped_25": {
    "CumulativeVarianceExplained": 0.3529861852,
    "Mask": "Edge",
    "Method": "EdgeRegressor",
    "Retained": false,
    "SingularValue": 108.6271520783,
    "VarianceExplained": 0.0037128785
  },
  "dropped_250": {
    "CumulativeVarianceExplained": 1.0,
    "Mask": "Edge",
    "Method": "EdgeRegressor",
    "Retained": false,
    "SingularValue": 0.0,
    "VarianceExplained": 0.0
  },
  "dropped_251": {
    "CumulativeVarianceExplained": 1.0,
    "Mask": "Edge",
    "Method": "EdgeRegressor",
    "Retained": false,
    "SingularValue": 0.0,
    "VarianceExplained": 0.0
  },
  "dropped_252": {
    "CumulativeVarianceExplained": 1.0,
    "Mask": "Edge",
    "Method": "EdgeRegressor",
    "Retained": false,
    "SingularValue": 0.0,
    "VarianceExplained": 0.0
  },
  "dropped_253": {
    "CumulativeVarianceExplained": 1.0,
    "Mask": "Edge",
    "Method": "EdgeRegressor",
    "Retained": false,
    "SingularValue": 0.0,
    "VarianceExplained": 0.0
  },
  "dropped_254": {
    "CumulativeVarianceExplained": 1.0,
    "Mask": "Edge",
    "Method": "EdgeRegressor",
    "Retained": false,
    "SingularValue": 0.0,
    "VarianceExplained": 0.0
  },
  "dropped_26": {
    "CumulativeVarianceExplained": 0.3566936592,
    "Mask": "Edge",
    "Method": "EdgeRegressor",
    "Retained": false,
    "SingularValue": 108.5480646282,
    "VarianceExplained": 0.003707474
  },
  "dropped_27": {
    "CumulativeVarianceExplained": 0.3603801131,
    "Mask": "Edge",
    "Method": "EdgeRegressor",
    "Retained": false,
    "SingularValue": 108.2399119126,
    "VarianceExplained": 0.0036864539
  },
  "dropped_28": {
    "CumulativeVarianceExplained": 0.3640647025,
    "Mask": "Edge",
    "Method": "EdgeRegressor",
    "Retained": false,
    "SingularValue": 108.2125367409,
    "VarianceExplained": 0.0036845894
  },
  "dropped_29": {
    "CumulativeVarianceExplained": 0.3677425579,
    "Mask": "Edge",
    "Method": "EdgeRegressor",
    "Retained": false,
    "SingularValue": 108.1136054766,
    "VarianceExplained": 0.0036778554
  },
  "dropped_3": {
    "CumulativeVarianceExplained": 0.2683483091,
    "Mask": "Edge",
    "Method": "EdgeRegressor",
    "Retained": false,
    "SingularValue": 113.0321543422,
    "VarianceExplained": 0.0040201102
  },
  "dropped_30": {
    "CumulativeVarianceExplained": 0.3714121348,
    "Mask": "Edge",
    "Method": "EdgeRegressor",
    "Retained": false,
    "SingularValue": 107.9918611604,
    "VarianceExplained": 0.0036695769
  },
  "dropped_31": {
    "CumulativeVarianceExplained": 0.3750737584,
    "Mask": "Edge",
    "Method": "EdgeRegressor",
    "Retained": false,
    "SingularValue": 107.8747686141,
    "VarianceExplained": 0.0036616236
  },
  "dropped_32": {
    "CumulativeVarianceExplained": 0.3787230691,
    "Mask": "Edge",
    "Method": "EdgeRegressor",
    "Retained": false,
    "SingularValue": 107.6932404635,
    "VarianceExplained": 0.0036493107
  },
  "dropped_33": {
    "CumulativeVarianceExplained": 0.3823543497,
    "Mask": "Edge",
    "Method": "EdgeRegressor",
    "Retained": false,
    "SingularValue": 107.4268718489,
    "VarianceExplained": 0.0036312806
  },
  "dropped_34": {
    "CumulativeVarianceExplained": 0.3859797636,
    "Mask": "Edge",
    "Method": "EdgeRegressor",
    "Retained": false,
    "SingularValue": 107.3400581401,
    "VarianceExplained": 0.0036254139
  },
  "dropped_35": {
    "CumulativeVarianceExplained": 0.3896001455,
    "Mask": "Edge",
    "Method": "EdgeRegressor",
    "Retained": false,
    "SingularValue": 107.2655388926,
    "VarianceExplained": 0.0036203819
  },
  "dropped_36": {
    "CumulativeVarianceExplained": 0.3932079028,
    "Mask": "Edge",
    "Method": "EdgeRegressor",
    "Retained": false,
    "SingularValue": 107.0783541323,
    "VarianceExplained": 0.0036077573
  },
  "dropped_37": {
    "CumulativeVarianceExplained": 0.3968077037,
    "Mask": "Edge",
    "Method": "EdgeRegressor",
    "Retained": false,
    "SingularValue": 106.9602149428,
    "VarianceExplained": 0.0035998009
  },
  "dropped_38": {
    "CumulativeVarianceExplained": 0.4003923599,
    "Mask": "Edge",
    "Method": "EdgeRegressor",
    "Retained": false,
    "SingularValue": 106.734981982,
    "VarianceExplained": 0.0035846562
  },
  "dropped_39": {
    "CumulativeVarianceExplained": 0.4039694579,
    "Mask": "Edge",
    "Method": "EdgeRegressor",
    "Retained": false,
    "SingularValue": 106.6223988077,
    "VarianceExplained": 0.003577098
  },
  "dropped_4": {
    "CumulativeVarianceExplained": 0.2723459258,
    "Mask": "Edge",
    "Method": "EdgeRegressor",
    "Retained": false,
    "SingularValue": 112.7154901799,
    "VarianceExplained": 0.0039976167
  },
  "dropped_40": {
    "CumulativeVarianceExplained": 0.407541368,
    "Mask": "Edge",
    "Method": "EdgeRegressor",
    "Retained": false,
    "SingularValue": 106.545052015,
    "VarianceExplained": 0.0035719101
  },
  "dropped_41": {
    "CumulativeVarianceExplained": 0.4111105877,
    "Mask": "Edge",
    "Method": "EdgeRegressor",
    "Retained": false,
    "SingularValue": 106.5049199782,
    "VarianceExplained": 0.0035692197
  },
  "dropped_42": {
    "CumulativeVarianceExplained": 0.4146734182,
    "Mask": "Edge",
    "Method": "EdgeRegressor",
    "Retained": false,
    "SingularValue": 106.409549893,
    "VarianceExplained": 0.0035628305
  },
  "dropped_43": {
    "CumulativeVarianceExplained": 0.4182222806,
    "Mask": "Edge",
    "Method": "EdgeRegressor",
    "Retained": false,
    "SingularValue": 106.2007565249,
    "VarianceExplained": 0.0035488624
  },
  "dropped_44": {
    "CumulativeVarianceExplained": 0.4217665361,
    "Mask": "Edge",
    "Method": "EdgeRegressor",
    "Retained": false,
    "SingularValue": 106.131802696,
    "VarianceExplained": 0.0035442555
  },
  "dropped_45": {
    "CumulativeVarianceExplained": 0.4252910279,
    "Mask": "Edge",
    "Method": "EdgeRegressor",
    "Retained": false,
    "SingularValue": 105.8354787504,
    "VarianceExplained": 0.0035244918
  },
  "dropped_46": {
    "CumulativeVarianceExplained": 0.4288125649,
    "Mask": "Edge",
    "Method": "EdgeRegressor",
    "Retained": false,
    "SingularValue": 105.7911049873,
    "VarianceExplained": 0.003521537
  },
  "dropped_47": {
    "CumulativeVarianceExplained": 0.4323206558,
    "Mask": "Edge",
    "Method": "EdgeRegressor",
    "Retained": false,
    "SingularValue": 105.5889446903,
    "VarianceExplained": 0.0035080909
  },
  "dropped_48": {
    "CumulativeVarianceExplained": 0.435824369,
    "Mask": "Edge",
    "Method": "EdgeRegressor",
    "Retained": false,
    "SingularValue": 105.5230415695,
    "VarianceExplained": 0.0035037132
  },
  "dropped_49": {
    "CumulativeVarianceExplained": 0.4393260518,
    "Mask": "Edge",
    "Method": "EdgeRegressor",
    "Retained": false,
    "SingularValue": 105.4924613299,
    "VarianceExplained": 0.0035016827
  },
  "dropped_5": {
    "CumulativeVarianceExplained": 0.2763355996,
    "Mask": "Edge",
    "Method": "EdgeRegressor",
    "Retained": false,
    "SingularValue": 112.6034561069,
    "VarianceExplained": 0.0039896738
  },
  "dropped_50": {
    "CumulativeVarianceExplained": 0.4428221458,
    "Mask": "Edge",
    "Method": "EdgeRegressor",
    "Retained": false,
    "SingularValue": 105.4082450945,
    "VarianceExplained": 0.0034960941
  },
  "dropped_51": {
    "CumulativeVarianceExplained": 0.4463025404,
    "Mask": "Edge",
    "Method": "EdgeRegressor",
    "Retained": false,
    "SingularValue": 105.1713065964,
    "VarianceExplained": 0.0034803946
  },
  "dropped_52": {
    "CumulativeVarianceExplained": 0.4497785137,
    "Mask": "Edge",
    "Method": "EdgeRegressor",
    "Retained": false,
    "SingularValue": 105.104483163,
    "VarianceExplained": 0.0034759733
  },
  "dropped_53": {
    "CumulativeVarianceExplained": 0.4532472724,
    "Mask": "Edge",
    "Method": "EdgeRegressor",
    "Retained": false,
    "SingularValue": 104.9953521243,
    "VarianceExplained": 0.0034687587
  },
  "dropped_54": {
    "CumulativeVarianceExplained": 0.4567100944,
    "Mask": "Edge",
    "Method": "EdgeRegressor",
    "Retained": false,
    "SingularValue": 104.905464531,
    "VarianceExplained": 0.003462822
  },
  "dropped_55": {
    "CumulativeVarianceExplained": 0.4601670422,
    "Mask": "Edge",
    "Method": "EdgeRegressor",
    "Retained": false,
    "SingularValue": 104.8164476318,
    "VarianceExplained": 0.0034569478
  },
  "dropped_56": {
    "CumulativeVarianceExplained": 0.4636107634,
    "Mask": "Edge",
    "Method": "EdgeRegressor",
    "Retained": false,
    "SingularValue": 104.6157382797,
    "VarianceExplained": 0.0034437213
  },
  "dropped_57": {
    "CumulativeVarianceExplained": 0.4670452172,
    "Mask": "Edge",
    "Method": "EdgeRegressor",
    "Retained": false,
    "SingularValue": 104.4748754601,
    "VarianceExplained": 0.0034344537
  },
  "dropped_58": {
    "CumulativeVarianceExplained": 0.4704763664,
    "Mask": "Edge",
    "Method": "EdgeRegressor",
    "Retained": false,
    "SingularValue": 104.4246023859,
    "VarianceExplained": 0.0034311492
  },
  "dropped_59": {
    "CumulativeVarianceExplained": 0.473897487,
    "Mask": "Edge",
    "Method": "EdgeRegressor",
    "Retained": false,
    "SingularValue": 104.2718845612,
    "VarianceExplained": 0.0034211207
  },
  "dropped_6": {
    "CumulativeVarianceExplained": 0.2803016025,
    "Mask": "Edge",
    "Method": "EdgeRegressor",
    "Retained": false,
    "SingularValue": 112.2689189117,
    "VarianceExplained": 0.0039660029
  },
  "dropped_60": {
    "CumulativeVarianceExplained": 0.4773120091,
    "Mask": "Edge",
    "Method": "EdgeRegressor",
    "Retained": false,
    "SingularValue": 104.1712766563,
    "VarianceExplained": 0.003414522
  },
  "dropped_61": {
    "CumulativeVarianceExplained": 0.4807180458,
    "Mask": "Edge",
    "Method": "EdgeRegressor",
    "Retained": false,
    "SingularValue": 104.0417603076,
    "VarianceExplained": 0.0034060367
  },
  "dropped_62": {
    "CumulativeVarianceExplained": 0.484119276,
    "Mask": "Edge",
    "Method": "EdgeRegressor",
    "Retained": false,
    "SingularValue": 103.9683229891,
    "VarianceExplained": 0.0034012302
  },
  "dropped_63": {
    "CumulativeVarianceExplained": 0.4875148348,
    "Mask": "Edge",
    "Method": "EdgeRegressor",
    "Retained": false,
    "SingularValue": 103.8816062304,
    "VarianceExplained": 0.0033955588
  },
  "dropped_64": {
    "CumulativeVarianceExplained": 0.4909019482,
    "Mask": "Edge",
    "Method": "EdgeRegressor",
    "Retained": false,
    "SingularValue": 103.7523396103,
    "VarianceExplained": 0.0033871134
  },
  "dropped_65": {
    "CumulativeVarianceExplained": 0.4942849455,
    "Mask": "Edge",
    "Method": "EdgeRegressor",
    "Retained": false,
    "SingularValue": 103.6892776097,
    "VarianceExplained": 0.0033829972
  },
  "dropped_66": {
    "CumulativeVarianceExplained": 0.4976597166,
    "Mask": "Edge",
    "Method": "EdgeRegressor",
    "Retained": false,
    "SingularValue": 103.5631362395,
    "VarianceExplained": 0.0033747712
  },
  "dropped_67": {
    "CumulativeVarianceExplained": 0.5010227986,
    "Mask": "Edge",
    "Method": "EdgeRegressor",
    "Retained": false,
    "SingularValue": 103.3836243366,
    "VarianceExplained": 0.003363082
  },
  "dropped_68": {
    "CumulativeVarianceExplained": 0.5043816472,
    "Mask": "Edge",
    "Method": "EdgeRegressor",
    "Retained": false,
    "SingularValue": 103.3185349154,
    "VarianceExplained": 0.0033588486
  },
  "dropped_69": {
    "CumulativeVarianceExplained": 0.5077283749,
    "Mask": "Edge",
    "Method": "EdgeRegressor",
    "Retained": false,
    "SingularValue": 103.1319470033,
    "VarianceExplained": 0.0033467277
  },
  "dropped_7": {
    "CumulativeVarianceExplained": 0.2842431163,
    "Mask": "Edge",
    "Method": "EdgeRegressor",
    "Retained": false,
    "SingularValue": 111.9217663809,
    "VarianceExplained": 0.0039415138
  },
  "dropped_70": {
    "CumulativeVarianceExplained": 0.5110718648,
    "Mask": "Edge",
    "Method": "EdgeRegressor",
    "Retained": false,
    "SingularValue": 103.082048403,
    "VarianceExplained": 0.00334349
  },
  "dropped_71": {
    "CumulativeVarianceExplained": 0.5144080477,
    "Mask": "Edge",
    "Method": "EdgeRegressor",
    "Retained": false,
    "SingularValue": 102.9693455477,
    "VarianceExplained": 0.0033361829
  },
  "dropped_72": {
    "CumulativeVarianceExplained": 0.5177399604,
    "Mask": "Edge",
    "Method": "EdgeRegressor",
    "Retained": false,
    "SingularValue": 102.9034254683,
    "VarianceExplained": 0.0033319127
  },
  "dropped_73": {
    "CumulativeVarianceExplained": 0.5210619277,
    "Mask": "Edge",
    "Method": "EdgeRegressor",
    "Retained": false,
    "SingularValue": 102.7497334226,
    "VarianceExplained": 0.0033219673
  },
  "dropped_74": {
    "CumulativeVarianceExplained": 0.5243786665,
    "Mask": "Edge",
    "Method": "EdgeRegressor",
    "Retained": false,
    "SingularValue": 102.6688421205,
    "VarianceExplained": 0.0033167388
  },
  "dropped_75": {
    "CumulativeVarianceExplained": 0.5276896446,
    "Mask": "Edge",
    "Method": "EdgeRegressor",
    "Retained": false,
    "SingularValue": 102.5796430769,
    "VarianceExplained": 0.0033109781
  },
  "dropped_76": {
    "CumulativeVarianceExplained": 0.5309861462,
    "Mask": "Edge",
    "Method": "EdgeRegressor",
    "Retained": false,
    "SingularValue": 102.3551439803,
    "VarianceExplained": 0.0032965016
  },
  "dropped_77": {
    "CumulativeVarianceExplained": 0.5342793069,
    "Mask": "Edge",
    "Method": "EdgeRegressor",
    "Retained": false,
    "SingularValue": 102.3032627278,
    "VarianceExplained": 0.0032931606
  },
  "dropped_78": {
    "CumulativeVarianceExplained": 0.5375604482,
    "Mask": "Edge",
    "Method": "EdgeRegressor",
    "Retained": false,
    "SingularValue": 102.116399869,
    "VarianceExplained": 0.0032811413
  },
  "dropped_79": {
    "CumulativeVarianceExplained": 0.540836521,
    "Mask": "Edge",
    "Method": "EdgeRegressor",
    "Retained": false,
    "SingularValue": 102.0374974736,
    "VarianceExplained": 0.0032760728
  },
  "dropped_8": {
    "CumulativeVarianceExplained": 0.2881791618,
    "Mask": "Edge",
    "Method": "EdgeRegressor",
    "Retained": false,
    "SingularValue": 111.8441007242,
    "VarianceExplained": 0.0039360455
  },
  "dropped_80": {
    "CumulativeVarianceExplained": 0.5441021604,
    "Mask": "Edge",
    "Method": "EdgeRegressor",
    "Retained": false,
    "SingularValue": 101.8748882299,
    "VarianceExplained": 0.0032656395
  },
  "dropped_81": {
    "CumulativeVarianceExplained": 0.5473637951,
    "Mask": "Edge",
    "Method": "EdgeRegressor",
    "Retained": false,
    "SingularValue": 101.8124022605,
    "VarianceExplained": 0.0032616347
  },
  "dropped_82": {
    "CumulativeVarianceExplained": 0.5506172513,
    "Mask": "Edge",
    "Method": "EdgeRegressor",
    "Retained": false,
    "SingularValue": 101.6846756485,
    "VarianceExplained": 0.0032534562
  },
  "dropped_83": {
    "CumulativeVarianceExplained": 0.5538678475,
    "Mask": "Edge",
    "Method": "EdgeRegressor",
    "Retained": false,
    "SingularValue": 101.6399739145,
    "VarianceExplained": 0.0032505963
  },
  "dropped_84": {
    "CumulativeVarianceExplained": 0.5571092992,
    "Mask": "Edge",
    "Method": "EdgeRegressor",
    "Retained": false,
    "SingularValue": 101.4969058853,
    "VarianceExplained": 0.0032414517
  },
  "dropped_85": {
    "CumulativeVarianceExplained": 0.5603457285,
    "Mask": "Edge",
    "Method": "EdgeRegressor",
    "Retained": false,
    "SingularValue": 101.4182453126,
    "VarianceExplained": 0.0032364293
  },
  "dropped_86": {
    "CumulativeVarianceExplained": 0.5635693055,
    "Mask": "Edge",
    "Method": "EdgeRegressor",
    "Retained": false,
    "SingularValue": 101.2166710671,
    "VarianceExplained": 0.003223577
  },
  "dropped_87": {
    "CumulativeVarianceExplained": 0.5667902293,
    "Mask": "Edge",
    "Method": "EdgeRegressor",
    "Retained": false,
    "SingularValue": 101.1750084692,
    "VarianceExplained": 0.0032209237
  },
  "dropped_88": {
    "CumulativeVarianceExplained": 0.5700085153,
    "Mask": "Edge",
    "Method": "EdgeRegressor",
    "Retained": false,
    "SingularValue": 101.1335722332,
    "VarianceExplained": 0.003218286
  },
  "dropped_89": {
    "CumulativeVarianceExplained": 0.573224993,
    "Mask": "Edge",
    "Method": "EdgeRegressor",
    "Retained": false,
    "SingularValue": 101.1051557483,
    "VarianceExplained": 0.0032164777
  },
  "dropped_9": {
    "CumulativeVarianceExplained": 0.2920932506,
    "Mask": "Edge",
    "Method": "EdgeRegressor",
    "Retained": false,
    "SingularValue": 111.5317106568,
    "VarianceExplained": 0.0039140888
  },
  "dropped_90": {
    "CumulativeVarianceExplained": 0.5764341351,
    "Mask": "Edge",
    "Method": "EdgeRegressor",
    "Retained": false,
    "SingularValue": 100.9897962065,
    "VarianceExplained": 0.003209142
  },
  "dropped_91": {
    "CumulativeVarianceExplained": 0.5796343475,
    "Mask": "Edge",
    "Method": "EdgeRegressor",
    "Retained": false,
    "SingularValue": 100.8491942781,
    "VarianceExplained": 0.0032002125
  },
  "dropped_92": {
    "CumulativeVarianceExplained": 0.5828313177,
    "Mask": "Edge",
    "Method": "EdgeRegressor",
    "Retained": false,
    "SingularValue": 100.7980940089,
    "VarianceExplained": 0.0031969702
  },
  "dropped_93": {
    "CumulativeVarianceExplained": 0.5860205728,
    "Mask": "Edge",
    "Method": "EdgeRegressor",
    "Retained": false,
    "SingularValue": 100.6763962548,
    "VarianceExplained": 0.0031892552
  },
  "dropped_94": {
    "CumulativeVarianceExplained": 0.5892051007,
    "Mask": "Edge",
    "Method": "EdgeRegressor",
    "Retained": false,
    "SingularValue": 100.6017537424,
    "VarianceExplained": 0.0031845278
  },
  "dropped_95": {
    "CumulativeVarianceExplained": 0.5923788121,
    "Mask": "Edge",
    "Method": "EdgeRegressor",
    "Retained": false,
    "SingularValue": 100.4307587289,
    "VarianceExplained": 0.0031737114
  },
  "dropped_96": {
    "CumulativeVarianceExplained": 0.5955451961,
    "Mask": "Edge",
    "Method": "EdgeRegressor",
    "Retained": false,
    "SingularValue": 100.3147554023,
    "VarianceExplained": 0.003166384
  },
  "dropped_97": {
    "CumulativeVarianceExplained": 0.5987038031,
    "Mask": "Edge",
    "Method": "EdgeRegressor",
    "Retained": false,
    "SingularValue": 100.1914877882,
    "VarianceExplained": 0.003158607
  },
  "dropped_98": {
    "CumulativeVarianceExplained": 0.6018574396,
    "Mask": "Edge",
    "Method": "EdgeRegressor",
    "Retained": false,
    "SingularValue": 100.1126240133,
    "VarianceExplained": 0.0031536365
  },
  "dropped_99": {
    "CumulativeVarianceExplained": 0.6050067109,
    "Mask": "Edge",
    "Method": "EdgeRegressor",
    "Retained": false,
    "SingularValue": 100.0433128233,
    "VarianceExplained": 0.0031492713
  },
  "edge_comp_00": {
    "CumulativeVarianceExplained": 0.0932272221,
    "Mask": "Edge",
    "Method": "EdgeRegressor",
    "Retained": true,
    "SingularValue": 544.3201347127,
    "VarianceExplained": 0.0932272221
  },
  "edge_comp_01": {
    "CumulativeVarianceExplained": 0.1105241253,
    "Mask": "Edge",
    "Method": "EdgeRegressor",
    "Retained": true,
    "SingularValue": 234.4591604226,
    "VarianceExplained": 0.0172969032
  },
  "edge_comp_02": {
    "CumulativeVarianceExplained": 0.1245645904,
    "Mask": "Edge",
    "Method": "EdgeRegressor",
    "Retained": true,
    "SingularValue": 211.238840329,
    "VarianceExplained": 0.0140404651
  },
  "edge_comp_03": {
    "CumulativeVarianceExplained": 0.1362314183,
    "Mask": "Edge",
    "Method": "EdgeRegressor",
    "Retained": true,
    "SingularValue": 192.5570494408,
    "VarianceExplained": 0.0116668279
  },
  "edge_comp_04": {
    "CumulativeVarianceExplained": 0.1472125529,
    "Mask": "Edge",
    "Method": "EdgeRegressor",
    "Retained": true,
    "SingularValue": 186.8128022532,
    "VarianceExplained": 0.0109811346
  },
  "edge_comp_05": {
    "CumulativeVarianceExplained": 0.1569239841,
    "Mask": "Edge",
    "Method": "EdgeRegressor",
    "Retained": true,
    "SingularValue": 175.6809402136,
    "VarianceExplained": 0.0097114312
  },
  "edge_comp_06": {
    "CumulativeVarianceExplained": 0.1653391332,
    "Mask": "Edge",
    "Method": "EdgeRegressor",
    "Retained": true,
    "SingularValue": 163.5362123642,
    "VarianceExplained": 0.0084151491
  },
  "edge_comp_07": {
    "CumulativeVarianceExplained": 0.1731460206,
    "Mask": "Edge",
    "Method": "EdgeRegressor",
    "Retained": true,
    "SingularValue": 157.5150243012,
    "VarianceExplained": 0.0078068874
  },
  "edge_comp_08": {
    "CumulativeVarianceExplained": 0.1804909564,
    "Mask": "Edge",
    "Method": "EdgeRegressor",
    "Retained": true,
    "SingularValue": 152.783702711,
    "VarianceExplained": 0.0073449358
  },
  "edge_comp_09": {
    "CumulativeVarianceExplained": 0.1868555114,
    "Mask": "Edge",
    "Method": "EdgeRegressor",
    "Retained": true,
    "SingularValue": 142.2220880358,
    "VarianceExplained": 0.006364555
  },
  "edge_comp_10": {
    "CumulativeVarianceExplained": 0.1930638124,
    "Mask": "Edge",
    "Method": "EdgeRegressor",
    "Retained": true,
    "SingularValue": 140.4654152791,
    "VarianceExplained": 0.0062083009
  },
  "edge_comp_11": {
    "CumulativeVarianceExplained": 0.1987869578,
    "Mask": "Edge",
    "Method": "EdgeRegressor",
    "Retained": true,
    "SingularValue": 134.8653601795,
    "VarianceExplained": 0.0057231454
  },
  "edge_comp_12": {
    "CumulativeVarianceExplained": 0.2042385524,
    "Mask": "Edge",
    "Method": "EdgeRegressor",
    "Retained": true,
    "SingularValue": 131.6269458319,
    "VarianceExplained": 0.0054515946
  },
  "edge_comp_13": {
    "CumulativeVarianceExplained": 0.2094072854,
    "Mask": "Edge",
    "Method": "EdgeRegressor",
    "Retained": true,
    "SingularValue": 128.1666636886,
    "VarianceExplained": 0.0051687331
  },
  "edge_comp_14": {
    "CumulativeVarianceExplained": 0.2139607719,
    "Mask": "Edge",
    "Method": "EdgeRegressor",
    "Retained": true,
    "SingularValue": 120.2970714144,
    "VarianceExplained": 0.0045534865
  },
  "edge_comp_15": {
    "CumulativeVarianceExplained": 0.2184605384,
    "Mask": "Edge",
    "Method": "EdgeRegressor",
    "Retained": true,
    "SingularValue": 119.5853595624,
    "VarianceExplained": 0.0044997664
  },
  "edge_comp_16": {
    "CumulativeVarianceExplained": 0.2228048308,
    "Mask": "Edge",
    "Method": "EdgeRegressor",
    "Retained": true,
    "SingularValue": 117.501267524,
    "VarianceExplained": 0.0043442924
  },
  "edge_comp_17": {
    "CumulativeVarianceExplained": 0.2270740293,
    "Mask": "Edge",
    "Method": "EdgeRegressor",
    "Retained": true,
    "SingularValue": 116.4812983868,
    "VarianceExplained": 0.0042691985
  },
  "edge_comp_18": {
    "CumulativeVarianceExplained": 0.2313407202,
    "Mask": "Edge",
    "Method": "EdgeRegressor",
    "Retained": true,
    "SingularValue": 116.4470837885,
    "VarianceExplained": 0.0042666909
  },
  "edge_comp_19": {
    "CumulativeVarianceExplained": 0.2355746214,
    "Mask": "Edge",
    "Method": "EdgeRegressor",
    "Retained": true,
    "SingularValue": 115.9987708904,
    "VarianceExplained": 0.0042339012
  },
  "edge_comp_20": {
    "CumulativeVarianceExplained": 0.2397725207,
    "Mask": "Edge",
    "Method": "EdgeRegressor",
    "Retained": true,
    "SingularValue": 115.5045347625,
    "VarianceExplained": 0.0041978993
  },
  "edge_comp_21": {
    "CumulativeVarianceExplained": 0.2439160717,
    "Mask": "Edge",
    "Method": "EdgeRegressor",
    "Retained": true,
    "SingularValue": 114.7544068349,
    "VarianceExplained": 0.004143551
  },
  "edge_comp_22": {
    "CumulativeVarianceExplained": 0.2480373867,
    "Mask": "Edge",
    "Method": "EdgeRegressor",
    "Retained": true,
    "SingularValue": 114.4460827659,
    "VarianceExplained": 0.004121315
  },
  "edge_comp_23": {
    "CumulativeVarianceExplained": 0.2521514814,
    "Mask": "Edge",
    "Method": "EdgeRegressor",
    "Retained": true,
    "SingularValue": 114.3457881586,
    "VarianceExplained": 0.0041140947
  },
  "t_comp_cor_00": {
    "CumulativeVarianceExplained": 0.3167077974,
    "Method": "tCompCor",
    "Retained": true,
    "SingularValue": 345.2529948137,
    "VarianceExplained": 0.3167077974
  },
  "t_comp_cor_01": {
    "CumulativeVarianceExplained": 0.4209606446,
    "Method": "tCompCor",
    "Retained": true,
    "SingularValue": 198.0852047449,
    "VarianceExplained": 0.1042528472
  },
  "t_comp_cor_02": {
    "CumulativeVarianceExplained": 0.5181282494,
    "Method": "tCompCor",
    "Retained": true,
    "SingularValue": 191.2356363212,
    "VarianceExplained": 0.0971676048
  },
  "w_comp_cor_00": {
    "CumulativeVarianceExplained": 0.0349572334,
    "Mask": "WM",
    "Method": "aCompCor",
    "Retained": true,
    "SingularValue": 95.3407546232,
    "VarianceExplained": 0.0349572334
  },
  "w_comp_cor_01": {
    "CumulativeVarianceExplained": 0.0458794105,
    "Mask": "WM",
    "Method": "aCompCor",
    "Retained": true,
    "SingularValue": 53.292324549,
    "VarianceExplained": 0.0109221771
  },
  "w_comp_cor_02": {
    "CumulativeVarianceExplained": 0.0556597307,
    "Mask": "WM",
    "Method": "aCompCor",
    "Retained": true,
    "SingularValue": 50.4297244178,
    "VarianceExplained": 0.0097803202
  },
  "w_comp_cor_03": {
    "CumulativeVarianceExplained": 0.065169646,
    "Mask": "WM",
    "Method": "aCompCor",
    "Retained": true,
    "SingularValue": 49.727700981,
    "VarianceExplained": 0.0095099153
  },
  "w_comp_cor_04": {
    "CumulativeVarianceExplained": 0.0742784608,
    "Mask": "WM",
    "Method": "aCompCor",
    "Retained": true,
    "SingularValue": 48.6677192577,
    "VarianceExplained": 0.0091088148
  },
  "w_comp_cor_05": {
    "CumulativeVarianceExplained": 0.0831747927,
    "Mask": "WM",
    "Method": "aCompCor",
    "Retained": true,
    "SingularValue": 48.096729553,
    "VarianceExplained": 0.0088963319
  },
  "w_comp_cor_06": {
    "CumulativeVarianceExplained": 0.0917810242,
    "Mask": "WM",
    "Method": "aCompCor",
    "Retained": true,
    "SingularValue": 47.3060374761,
    "VarianceExplained": 0.0086062316
  },
  "w_comp_cor_07": {
    "CumulativeVarianceExplained": 0.1000556206,
    "Mask": "WM",
    "Method": "aCompCor",
    "Retained": true,
    "SingularValue": 46.3856307498,
    "VarianceExplained": 0.0082745964
  },
  "w_comp_cor_08": {
    "CumulativeVarianceExplained": 0.108256413,
    "Mask": "WM",
    "Method": "aCompCor",
    "Retained": true,
    "SingularValue": 46.1783028055,
    "VarianceExplained": 0.0082007924
  },
  "w_comp_cor_09": {
    "CumulativeVarianceExplained": 0.1163989974,
    "Mask": "WM",
    "Method": "aCompCor",
    "Retained": true,
    "SingularValue": 46.0141276817,
    "VarianceExplained": 0.0081425844
  },
  "w_comp_cor_10": {
    "CumulativeVarianceExplained": 0.1244375624,
    "Mask": "WM",
    "Method": "aCompCor",
    "Retained": true,
    "SingularValue": 45.7192734691,
    "VarianceExplained": 0.0080385649
  },
  "w_comp_cor_11": {
    "CumulativeVarianceExplained": 0.1324730973,
    "Mask": "WM",
    "Method": "aCompCor",
    "Retained": true,
    "SingularValue": 45.7106559072,
    "VarianceExplained": 0.0080355349
  },
  "w_comp_cor_12": {
    "CumulativeVarianceExplained": 0.1403381005,
    "Mask": "WM",
    "Method": "aCompCor",
    "Retained": true,
    "SingularValue": 45.2230147048,
    "VarianceExplained": 0.0078650032
  },
  "w_comp_cor_13": {
    "CumulativeVarianceExplained": 0.1481523538,
    "Mask": "WM",
    "Method": "aCompCor",
    "Retained": true,
    "SingularValue": 45.076875008,
    "VarianceExplained": 0.0078142533
  },
  "w_comp_cor_14": {
    "CumulativeVarianceExplained": 0.1558878557,
    "Mask": "WM",
    "Method": "aCompCor",
    "Retained": true,
    "SingularValue": 44.8491592429,
    "VarianceExplained": 0.0077355019
  },
  "w_comp_cor_15": {
    "CumulativeVarianceExplained": 0.1634926463,
    "Mask": "WM",
    "Method": "aCompCor",
    "Retained": true,
    "SingularValue": 44.4686235576,
    "VarianceExplained": 0.0076047906
  },
  "w_comp_cor_16": {
    "CumulativeVarianceExplained": 0.1710307871,
    "Mask": "WM",
    "Method": "aCompCor",
    "Retained": true,
    "SingularValue": 44.2733292416,
    "VarianceExplained": 0.0075381408
  },
  "w_comp_cor_17": {
    "CumulativeVarianceExplained": 0.1784413383,
    "Mask": "WM",
    "Method": "aCompCor",
    "Retained": true,
    "SingularValue": 43.8970477178,
    "VarianceExplained": 0.0074105512
  },
  "w_comp_cor_18": {
    "CumulativeVarianceExplained": 0.1858172822,
    "Mask": "WM",
    "Method": "aCompCor",
    "Retained": true,
    "SingularValue": 43.794428463,
    "VarianceExplained": 0.007375944
  },
  "w_comp_cor_19": {
    "CumulativeVarianceExplained": 0.1931572278,
    "Mask": "WM",
    "Method": "aCompCor",
    "Retained": true,
    "SingularValue": 43.6874280509,
    "VarianceExplained": 0.0073399456
  },
  "w_comp_cor_20": {
    "CumulativeVarianceExplained": 0.2004536301,
    "Mask": "WM",
    "Method": "aCompCor",
    "Retained": true,
    "SingularValue": 43.557650167,
    "VarianceExplained": 0.0072964023
  },
  "w_comp_cor_21": {
    "CumulativeVarianceExplained": 0.2076952441,
    "Mask": "WM",
    "Method": "aCompCor",
    "Retained": true,
    "SingularValue": 43.3938060945,
    "VarianceExplained": 0.007241614
  },
  "w_comp_cor_22": {
    "CumulativeVarianceExplained": 0.21483921,
    "Mask": "WM",
    "Method": "aCompCor",
    "Retained": true,
    "SingularValue": 43.1002454794,
    "VarianceExplained": 0.0071439659
  },
  "w_comp_cor_23": {
    "CumulativeVarianceExplained": 0.2218904871,
    "Mask": "WM",
    "Method": "aCompCor",
    "Retained": true,
    "SingularValue": 42.8197325532,
    "VarianceExplained": 0.0070512772
  },
  "w_comp_cor_24": {
    "CumulativeVarianceExplained": 0.2288975875,
    "Mask": "WM",
    "Method": "aCompCor",
    "Retained": true,
    "SingularValue": 42.6853872478,
    "VarianceExplained": 0.0070071003
  },
  "w_comp_cor_25": {
    "CumulativeVarianceExplained": 0.235827321,
    "Mask": "WM",
    "Method": "aCompCor",
    "Retained": true,
    "SingularValue": 42.4490841118,
    "VarianceExplained": 0.0069297335
  },
  "w_comp_cor_26": {
    "CumulativeVarianceExplained": 0.2426922317,
    "Mask": "WM",
    "Method": "aCompCor",
    "Retained": true,
    "SingularValue": 42.250077047,
    "VarianceExplained": 0.0068649107
  },
  "w_comp_cor_27": {
    "CumulativeVarianceExplained": 0.2494701353,
    "Mask": "WM",
    "Method": "aCompCor",
    "Retained": true,
    "SingularValue": 41.9814807219,
    "VarianceExplained": 0.0067779036
  },
  "w_comp_cor_28": {
    "CumulativeVarianceExplained": 0.256208365,
    "Mask": "WM",
    "Method": "aCompCor",
    "Retained": true,
    "SingularValue": 41.8584326721,
    "VarianceExplained": 0.0067382297
  },
  "w_comp_cor_29": {
    "CumulativeVarianceExplained": 0.2628874738,
    "Mask": "WM",
    "Method": "aCompCor",
    "Retained": true,
    "SingularValue": 41.6743963749,
    "VarianceExplained": 0.0066791088
  },
  "w_comp_cor_30": {
    "CumulativeVarianceExplained": 0.2694991448,
    "Mask": "WM",
    "Method": "aCompCor",
    "Retained": true,
    "SingularValue": 41.4634727681,
    "VarianceExplained": 0.006611671
  },
  "w_comp_cor_31": {
    "CumulativeVarianceExplained": 0.2760174079,
    "Mask": "WM",
    "Method": "aCompCor",
    "Retained": true,
    "SingularValue": 41.169538805,
    "VarianceExplained": 0.0065182631
  },
  "w_comp_cor_32": {
    "CumulativeVarianceExplained": 0.2825051874,
    "Mask": "WM",
    "Method": "aCompCor",
    "Retained": true,
    "SingularValue": 41.0731582492,
    "VarianceExplained": 0.0064877795
  },
  "w_comp_cor_33": {
    "CumulativeVarianceExplained": 0.2889250805,
    "Mask": "WM",
    "Method": "aCompCor",
    "Retained": true,
    "SingularValue": 40.8577038708,
    "VarianceExplained": 0.0064198931
  },
  "w_comp_cor_34": {
    "CumulativeVarianceExplained": 0.2953308988,
    "Mask": "WM",
    "Method": "aCompCor",
    "Retained": true,
    "SingularValue": 40.8128914007,
    "VarianceExplained": 0.0064058182
  },
  "w_comp_cor_35": {
    "CumulativeVarianceExplained": 0.3016626242,
    "Mask": "WM",
    "Method": "aCompCor",
    "Retained": true,
    "SingularValue": 40.5761739676,
    "VarianceExplained": 0.0063317254
  },
  "w_comp_cor_36": {
    "CumulativeVarianceExplained": 0.3079245583,
    "Mask": "WM",
    "Method": "aCompCor",
    "Retained": true,
    "SingularValue": 40.3519293651,
    "VarianceExplained": 0.0062619341
  },
  "w_comp_cor_37": {
    "CumulativeVarianceExplained": 0.3141750286,
    "Mask": "WM",
    "Method": "aCompCor",
    "Retained": true,
    "SingularValue": 40.314976196,
    "VarianceExplained": 0.0062504704
  },
  "w_comp_cor_38": {
    "CumulativeVarianceExplained": 0.3204038966,
    "Mask": "WM",
    "Method": "aCompCor",
    "Retained": true,
    "SingularValue": 40.2452490485,
    "VarianceExplained": 0.0062288679
  },
  "w_comp_cor_39": {
    "CumulativeVarianceExplained": 0.326558331,
    "Mask": "WM",
    "Method": "aCompCor",
    "Retained": true,
    "SingularValue": 40.0040656449,
    "VarianceExplained": 0.0061544344
  },
  "w_comp_cor_40": {
    "CumulativeVarianceExplained": 0.3326769722,
    "Mask": "WM",
    "Method": "aCompCor",
    "Retained": true,
    "SingularValue": 39.887567518,
    "VarianceExplained": 0.0061186412
  },
  "w_comp_cor_41": {
    "CumulativeVarianceExplained": 0.338778436,
    "Mask": "WM",
    "Method": "aCompCor",
    "Retained": true,
    "SingularValue": 39.8315381118,
    "VarianceExplained": 0.0061014638
  },
  "w_comp_cor_42": {
    "CumulativeVarianceExplained": 0.3448245002,
    "Mask": "WM",
    "Method": "aCompCor",
    "Retained": true,
    "SingularValue": 39.6502960163,
    "VarianceExplained": 0.0060460642
  },
  "w_comp_cor_43": {
    "CumulativeVarianceExplained": 0.3507589611,
    "Mask": "WM",
    "Method": "aCompCor",
    "Retained": true,
    "SingularValue": 39.2826424346,
    "VarianceExplained": 0.0059344609
  },
  "w_comp_cor_44": {
    "CumulativeVarianceExplained": 0.3566790827,
    "Mask": "WM",
    "Method": "aCompCor",
    "Retained": true,
    "SingularValue": 39.2351548163,
    "VarianceExplained": 0.0059201216
  },
  "w_comp_cor_45": {
    "CumulativeVarianceExplained": 0.3625445017,
    "Mask": "WM",
    "Method": "aCompCor",
    "Retained": true,
    "SingularValue": 39.0534658783,
    "VarianceExplained": 0.0058654191
  },
  "w_comp_cor_46": {
    "CumulativeVarianceExplained": 0.3684051229,
    "Mask": "WM",
    "Method": "aCompCor",
    "Retained": true,
    "SingularValue": 39.0374897027,
    "VarianceExplained": 0.0058606212
  },
  "w_comp_cor_47": {
    "CumulativeVarianceExplained": 0.374212476,
    "Mask": "WM",
    "Method": "aCompCor",
    "Retained": true,
    "SingularValue": 38.8596757455,
    "VarianceExplained": 0.0058073531
  },
  "w_comp_cor_48": {
    "CumulativeVarianceExplained": 0.3800069061,
    "Mask": "WM",
    "Method": "aCompCor",
    "Retained": true,
    "SingularValue": 38.8164151175,
    "VarianceExplained": 0.0057944301
  },
  "w_comp_cor_49": {
    "CumulativeVarianceExplained": 0.3857444589,
    "Mask": "WM",
    "Method": "aCompCor",
    "Retained": true,
    "SingularValue": 38.6254368959,
    "VarianceExplained": 0.0057375528
  },
  "w_comp_cor_50": {
    "CumulativeVarianceExplained": 0.3914655644,
    "Mask": "WM",
    "Method": "aCompCor",
    "Retained": true,
    "SingularValue": 38.5700352531,
    "VarianceExplained": 0.0057211055
  },
  "w_comp_cor_51": {
    "CumulativeVarianceExplained": 0.3971065224,
    "Mask": "WM",
    "Method": "aCompCor",
    "Retained": true,
    "SingularValue": 38.2989169184,
    "VarianceExplained": 0.005640958
  },
  "w_comp_cor_52": {
    "CumulativeVarianceExplained": 0.4026777883,
    "Mask": "WM",
    "Method": "aCompCor",
    "Retained": true,
    "SingularValue": 38.0615965073,
    "VarianceExplained": 0.0055712659
  },
  "w_comp_cor_53": {
    "CumulativeVarianceExplained": 0.4082365603,
    "Mask": "WM",
    "Method": "aCompCor",
    "Retained": true,
    "SingularValue": 38.0188946966,
    "VarianceExplained": 0.005558772
  },
  "w_comp_cor_54": {
    "CumulativeVarianceExplained": 0.41377727,
    "Mask": "WM",
    "Method": "aCompCor",
    "Retained": true,
    "SingularValue": 37.9570766138,
    "VarianceExplained": 0.0055407097
  },
  "w_comp_cor_55": {
    "CumulativeVarianceExplained": 0.4192590536,
    "Mask": "WM",
    "Method": "aCompCor",
    "Retained": true,
    "SingularValue": 37.7546980432,
    "VarianceExplained": 0.0054817836
  },
  "w_comp_cor_56": {
    "CumulativeVarianceExplained": 0.4246579253,
    "Mask": "WM",
    "Method": "aCompCor",
    "Retained": true,
    "SingularValue": 37.4680905938,
    "VarianceExplained": 0.0053988717
  },
  "w_comp_cor_57": {
    "CumulativeVarianceExplained": 0.4300353531,
    "Mask": "WM",
    "Method": "aCompCor",
    "Retained": true,
    "SingularValue": 37.3936064708,
    "VarianceExplained": 0.0053774278
  },
  "w_comp_cor_58": {
    "CumulativeVarianceExplained": 0.4353824367,
    "Mask": "WM",
    "Method": "aCompCor",
    "Retained": true,
    "SingularValue": 37.2879530985,
    "VarianceExplained": 0.0053470836
  },
  "w_comp_cor_59": {
    "CumulativeVarianceExplained": 0.4406585079,
    "Mask": "WM",
    "Method": "aCompCor",
    "Retained": true,
    "SingularValue": 37.039522528,
    "VarianceExplained": 0.0052760712
  },
  "w_comp_cor_60": {
    "CumulativeVarianceExplained": 0.4459083929,
    "Mask": "WM",
    "Method": "aCompCor",
    "Retained": true,
    "SingularValue": 36.947491352,
    "VarianceExplained": 0.0052498851
  },
  "w_comp_cor_61": {
    "CumulativeVarianceExplained": 0.4511408243,
    "Mask": "WM",
    "Method": "aCompCor",
    "Retained": true,
    "SingularValue": 36.8860225597,
    "VarianceExplained": 0.0052324314
  },
  "w_comp_cor_62": {
    "CumulativeVarianceExplained": 0.4563419002,
    "Mask": "WM",
    "Method": "aCompCor",
    "Retained": true,
    "SingularValue": 36.7753364919,
    "VarianceExplained": 0.0052010759
  },
  "w_comp_cor_63": {
    "CumulativeVarianceExplained": 0.461499605,
    "Mask": "WM",
    "Method": "aCompCor",
    "Retained": true,
    "SingularValue": 36.6216828799,
    "VarianceExplained": 0.0051577048
  },
  "w_comp_cor_64": {
    "CumulativeVarianceExplained": 0.4666475829,
    "Mask": "WM",
    "Method": "aCompCor",
    "Retained": true,
    "SingularValue": 36.5871343872,
    "VarianceExplained": 0.0051479779
  },
  "w_comp_cor_65": {
    "CumulativeVarianceExplained": 0.4717542319,
    "Mask": "WM",
    "Method": "aCompCor",
    "Retained": true,
    "SingularValue": 36.4399740905,
    "VarianceExplained": 0.0051066489
  },
  "w_comp_cor_66": {
    "CumulativeVarianceExplained": 0.4768223691,
    "Mask": "WM",
    "Method": "aCompCor",
    "Retained": true,
    "SingularValue": 36.3023081658,
    "VarianceExplained": 0.0050681372
  },
  "w_comp_cor_67": {
    "CumulativeVarianceExplained": 0.4818685336,
    "Mask": "WM",
    "Method": "aCompCor",
    "Retained": true,
    "SingularValue": 36.2235292098,
    "VarianceExplained": 0.0050461645
  },
  "w_comp_cor_68": {
    "CumulativeVarianceExplained": 0.4868415043,
    "Mask": "WM",
    "Method": "aCompCor",
    "Retained": true,
    "SingularValue": 35.9598614294,
    "VarianceExplained": 0.0049729707
  },
  "w_comp_cor_69": {
    "CumulativeVarianceExplained": 0.4917616008,
    "Mask": "WM",
    "Method": "aCompCor",
    "Retained": true,
    "SingularValue": 35.7681821158,
    "VarianceExplained": 0.0049200965
  },
  "w_comp_cor_70": {
    "CumulativeVarianceExplained": 0.496624339,
    "Mask": "WM",
    "Method": "aCompCor",
    "Retained": true,
    "SingularValue": 35.5590786545,
    "VarianceExplained": 0.0048627381
  },
  "w_comp_cor_71": {
    "CumulativeVarianceExplained": 0.5014396296,
    "Mask": "WM",
    "Method": "aCompCor",
    "Retained": true,
    "SingularValue": 35.3851719237,
    "VarianceExplained": 0.0048152906
  }
}